[
  {
    "y": "473",
    "x": "583",
    "value": 0.001
  },
  {
    "y": "473",
    "x": "585",
    "value": 0.001
  },
  {
    "y": "473",
    "x": "588",
    "value": 0.001
  },
  {
    "y": "473",
    "x": "591",
    "value": 0.001
  },
  {
    "y": "478",
    "x": "583",
    "value": 0.028
  },
  {
    "y": "478",
    "x": "585",
    "value": 0.021
  },
  {
    "y": "478",
    "x": "588",
    "value": 0.006
  },
  {
    "y": "478",
    "x": "591",
    "value": 0.003
  },
  {
    "y": "478",
    "x": "593",
    "value": 0.001
  },
  {
    "y": "482",
    "x": "577",
    "value": 0.115
  },
  {
    "y": "482",
    "x": "580",
    "value": 0.229
  },
  {
    "y": "482",
    "x": "583",
    "value": 0.283
  },
  {
    "y": "482",
    "x": "585",
    "value": 0.221
  },
  {
    "y": "482",
    "x": "588",
    "value": 0.098
  },
  {
    "y": "482",
    "x": "591",
    "value": 0.026
  },
  {
    "y": "482",
    "x": "593",
    "value": 0.007
  },
  {
    "y": "487",
    "x": "569",
    "value": 0.189
  },
  {
    "y": "487",
    "x": "572",
    "value": 0.409
  },
  {
    "y": "487",
    "x": "574",
    "value": 0.615
  },
  {
    "y": "487",
    "x": "577",
    "value": 0.733
  },
  {
    "y": "487",
    "x": "580",
    "value": 0.734
  },
  {
    "y": "487",
    "x": "583",
    "value": 0.714
  },
  {
    "y": "487",
    "x": "585",
    "value": 0.661
  },
  {
    "y": "487",
    "x": "588",
    "value": 0.583
  },
  {
    "y": "487",
    "x": "591",
    "value": 0.379
  },
  {
    "y": "487",
    "x": "593",
    "value": 0.092
  },
  {
    "y": "487",
    "x": "596",
    "value": 0.001
  },
  {
    "y": "491",
    "x": "566",
    "value": 0.283
  },
  {
    "y": "491",
    "x": "569",
    "value": 0.612
  },
  {
    "y": "491",
    "x": "572",
    "value": 0.731
  },
  {
    "y": "491",
    "x": "574",
    "value": 0.824
  },
  {
    "y": "491",
    "x": "577",
    "value": 0.885
  },
  {
    "y": "491",
    "x": "580",
    "value": 0.898
  },
  {
    "y": "491",
    "x": "583",
    "value": 0.887
  },
  {
    "y": "491",
    "x": "585",
    "value": 0.86
  },
  {
    "y": "491",
    "x": "588",
    "value": 0.819
  },
  {
    "y": "491",
    "x": "591",
    "value": 0.604
  },
  {
    "y": "491",
    "x": "593",
    "value": 0.141
  },
  {
    "y": "491",
    "x": "596",
    "value": 0.001
  },
  {
    "y": "496",
    "x": "561",
    "value": 0.206
  },
  {
    "y": "496",
    "x": "564",
    "value": 0.535
  },
  {
    "y": "496",
    "x": "566",
    "value": 0.842
  },
  {
    "y": "496",
    "x": "569",
    "value": 0.947
  },
  {
    "y": "496",
    "x": "572",
    "value": 1.013
  },
  {
    "y": "496",
    "x": "574",
    "value": 1.068
  },
  {
    "y": "496",
    "x": "577",
    "value": 1.111
  },
  {
    "y": "496",
    "x": "580",
    "value": 1.14
  },
  {
    "y": "496",
    "x": "583",
    "value": 1.157
  },
  {
    "y": "496",
    "x": "585",
    "value": 1.163
  },
  {
    "y": "496",
    "x": "588",
    "value": 1.154
  },
  {
    "y": "496",
    "x": "591",
    "value": 1.095
  },
  {
    "y": "496",
    "x": "593",
    "value": 0.994
  },
  {
    "y": "500",
    "x": "556",
    "value": 0.163
  },
  {
    "y": "500",
    "x": "558",
    "value": 0.404
  },
  {
    "y": "500",
    "x": "561",
    "value": 0.595
  },
  {
    "y": "500",
    "x": "564",
    "value": 0.658
  },
  {
    "y": "500",
    "x": "566",
    "value": 0.781
  },
  {
    "y": "500",
    "x": "569",
    "value": 0.927
  },
  {
    "y": "500",
    "x": "572",
    "value": 1.033
  },
  {
    "y": "500",
    "x": "574",
    "value": 1.129
  },
  {
    "y": "500",
    "x": "577",
    "value": 1.206
  },
  {
    "y": "500",
    "x": "580",
    "value": 1.273
  },
  {
    "y": "500",
    "x": "583",
    "value": 1.344
  },
  {
    "y": "500",
    "x": "585",
    "value": 1.437
  },
  {
    "y": "500",
    "x": "588",
    "value": 1.597
  },
  {
    "y": "500",
    "x": "591",
    "value": 2
  },
  {
    "y": "500",
    "x": "593",
    "value": 3.613
  },
  {
    "y": "500",
    "x": "596",
    "value": 4.582
  },
  {
    "y": "500",
    "x": "599",
    "value": 2.764
  },
  {
    "y": "504",
    "x": "556",
    "value": 0.605
  },
  {
    "y": "504",
    "x": "558",
    "value": 0.595
  },
  {
    "y": "504",
    "x": "561",
    "value": 0.674
  },
  {
    "y": "504",
    "x": "564",
    "value": 0.715
  },
  {
    "y": "504",
    "x": "566",
    "value": 0.678
  },
  {
    "y": "504",
    "x": "569",
    "value": 0.761
  },
  {
    "y": "504",
    "x": "572",
    "value": 0.987
  },
  {
    "y": "504",
    "x": "574",
    "value": 1.15
  },
  {
    "y": "504",
    "x": "577",
    "value": 1.288
  },
  {
    "y": "504",
    "x": "580",
    "value": 1.406
  },
  {
    "y": "504",
    "x": "583",
    "value": 1.539
  },
  {
    "y": "504",
    "x": "585",
    "value": 1.726
  },
  {
    "y": "504",
    "x": "588",
    "value": 2.048
  },
  {
    "y": "504",
    "x": "591",
    "value": 2.802
  },
  {
    "y": "504",
    "x": "593",
    "value": 5.213
  },
  {
    "y": "504",
    "x": "596",
    "value": 7.312
  },
  {
    "y": "504",
    "x": "599",
    "value": 7.535
  },
  {
    "y": "504",
    "x": "601",
    "value": 6.646
  },
  {
    "y": "504",
    "x": "604",
    "value": 6.316
  },
  {
    "y": "504",
    "x": "607",
    "value": 2.998
  },
  {
    "y": "504",
    "x": "609",
    "value": 2.646
  },
  {
    "y": "504",
    "x": "612",
    "value": 2.64
  },
  {
    "y": "504",
    "x": "615",
    "value": 0.032
  },
  {
    "y": "504",
    "x": "617",
    "value": 0.012
  },
  {
    "y": "504",
    "x": "620",
    "value": 0.005
  },
  {
    "y": "504",
    "x": "623",
    "value": 0.002
  },
  {
    "y": "509",
    "x": "550",
    "value": 0.333
  },
  {
    "y": "509",
    "x": "553",
    "value": 0.556
  },
  {
    "y": "509",
    "x": "556",
    "value": 0.636
  },
  {
    "y": "509",
    "x": "558",
    "value": 0.698
  },
  {
    "y": "509",
    "x": "561",
    "value": 0.755
  },
  {
    "y": "509",
    "x": "564",
    "value": 0.788
  },
  {
    "y": "509",
    "x": "566",
    "value": 0.812
  },
  {
    "y": "509",
    "x": "569",
    "value": 0.787
  },
  {
    "y": "509",
    "x": "572",
    "value": 0.903
  },
  {
    "y": "509",
    "x": "574",
    "value": 1.186
  },
  {
    "y": "509",
    "x": "577",
    "value": 1.399
  },
  {
    "y": "509",
    "x": "580",
    "value": 1.573
  },
  {
    "y": "509",
    "x": "583",
    "value": 1.758
  },
  {
    "y": "509",
    "x": "585",
    "value": 2.015
  },
  {
    "y": "509",
    "x": "588",
    "value": 2.432
  },
  {
    "y": "509",
    "x": "591",
    "value": 3.357
  },
  {
    "y": "509",
    "x": "593",
    "value": 2.568
  },
  {
    "y": "509",
    "x": "596",
    "value": 5.125
  },
  {
    "y": "509",
    "x": "599",
    "value": 8.101
  },
  {
    "y": "509",
    "x": "601",
    "value": 6.305
  },
  {
    "y": "509",
    "x": "604",
    "value": 5.881
  },
  {
    "y": "509",
    "x": "607",
    "value": 2.973
  },
  {
    "y": "509",
    "x": "609",
    "value": 0.036
  },
  {
    "y": "509",
    "x": "612",
    "value": 0.032
  },
  {
    "y": "509",
    "x": "615",
    "value": 0.018
  },
  {
    "y": "509",
    "x": "617",
    "value": 0.017
  },
  {
    "y": "509",
    "x": "620",
    "value": 0.012
  },
  {
    "y": "509",
    "x": "623",
    "value": 0.009
  },
  {
    "y": "513",
    "x": "548",
    "value": 0.137
  },
  {
    "y": "513",
    "x": "550",
    "value": 0.433
  },
  {
    "y": "513",
    "x": "553",
    "value": 0.66
  },
  {
    "y": "513",
    "x": "556",
    "value": 0.784
  },
  {
    "y": "513",
    "x": "558",
    "value": 0.86
  },
  {
    "y": "513",
    "x": "561",
    "value": 0.916
  },
  {
    "y": "513",
    "x": "564",
    "value": 0.953
  },
  {
    "y": "513",
    "x": "566",
    "value": 0.978
  },
  {
    "y": "513",
    "x": "569",
    "value": 1.005
  },
  {
    "y": "513",
    "x": "572",
    "value": 1.016
  },
  {
    "y": "513",
    "x": "574",
    "value": 1.229
  },
  {
    "y": "513",
    "x": "577",
    "value": 1.596
  },
  {
    "y": "513",
    "x": "580",
    "value": 1.851
  },
  {
    "y": "513",
    "x": "583",
    "value": 2.087
  },
  {
    "y": "513",
    "x": "585",
    "value": 2.417
  },
  {
    "y": "513",
    "x": "588",
    "value": 3.158
  },
  {
    "y": "513",
    "x": "591",
    "value": 5.917
  },
  {
    "y": "513",
    "x": "593",
    "value": 8.691
  },
  {
    "y": "513",
    "x": "596",
    "value": 8.457
  },
  {
    "y": "513",
    "x": "599",
    "value": 7.882
  },
  {
    "y": "513",
    "x": "601",
    "value": 6.853
  },
  {
    "y": "513",
    "x": "604",
    "value": 7.117
  },
  {
    "y": "513",
    "x": "607",
    "value": 4.911
  },
  {
    "y": "513",
    "x": "609",
    "value": 3.261
  },
  {
    "y": "513",
    "x": "612",
    "value": 0.044
  },
  {
    "y": "513",
    "x": "615",
    "value": 0.019
  },
  {
    "y": "513",
    "x": "617",
    "value": 0.014
  },
  {
    "y": "513",
    "x": "620",
    "value": 0.007
  },
  {
    "y": "513",
    "x": "623",
    "value": 0.016
  },
  {
    "y": "518",
    "x": "545",
    "value": 0.986
  },
  {
    "y": "518",
    "x": "548",
    "value": 0.406
  },
  {
    "y": "518",
    "x": "550",
    "value": 0.311
  },
  {
    "y": "518",
    "x": "553",
    "value": 0.346
  },
  {
    "y": "518",
    "x": "556",
    "value": 0.491
  },
  {
    "y": "518",
    "x": "558",
    "value": 0.592
  },
  {
    "y": "518",
    "x": "561",
    "value": 0.668
  },
  {
    "y": "518",
    "x": "564",
    "value": 0.725
  },
  {
    "y": "518",
    "x": "566",
    "value": 0.759
  },
  {
    "y": "518",
    "x": "569",
    "value": 0.802
  },
  {
    "y": "518",
    "x": "572",
    "value": 0.848
  },
  {
    "y": "518",
    "x": "574",
    "value": 1
  },
  {
    "y": "518",
    "x": "577",
    "value": 1.362
  },
  {
    "y": "518",
    "x": "580",
    "value": 1.737
  },
  {
    "y": "518",
    "x": "583",
    "value": 2.069
  },
  {
    "y": "518",
    "x": "585",
    "value": 2.667
  },
  {
    "y": "518",
    "x": "588",
    "value": 4.394
  },
  {
    "y": "518",
    "x": "591",
    "value": 7.213
  },
  {
    "y": "518",
    "x": "593",
    "value": 8.937
  },
  {
    "y": "518",
    "x": "596",
    "value": 9.199
  },
  {
    "y": "518",
    "x": "599",
    "value": 9.09
  },
  {
    "y": "518",
    "x": "601",
    "value": 8.911
  },
  {
    "y": "518",
    "x": "604",
    "value": 9.411
  },
  {
    "y": "518",
    "x": "607",
    "value": 10.362
  },
  {
    "y": "518",
    "x": "609",
    "value": 11.503
  },
  {
    "y": "518",
    "x": "612",
    "value": 11.104
  },
  {
    "y": "518",
    "x": "615",
    "value": 10.82
  },
  {
    "y": "518",
    "x": "617",
    "value": 9.716
  },
  {
    "y": "518",
    "x": "620",
    "value": 4.613
  },
  {
    "y": "518",
    "x": "623",
    "value": 0.062
  },
  {
    "y": "518",
    "x": "626",
    "value": 0.037
  },
  {
    "y": "518",
    "x": "628",
    "value": 0.018
  },
  {
    "y": "518",
    "x": "631",
    "value": 0.004
  },
  {
    "y": "522",
    "x": "542",
    "value": 0.613
  },
  {
    "y": "522",
    "x": "599",
    "value": 2.788
  },
  {
    "y": "522",
    "x": "601",
    "value": 6.693
  },
  {
    "y": "522",
    "x": "604",
    "value": 8.14
  },
  {
    "y": "522",
    "x": "607",
    "value": 9.218
  },
  {
    "y": "522",
    "x": "609",
    "value": 10.261
  },
  {
    "y": "522",
    "x": "612",
    "value": 10.803
  },
  {
    "y": "522",
    "x": "615",
    "value": 10.66
  },
  {
    "y": "522",
    "x": "617",
    "value": 10.55
  },
  {
    "y": "522",
    "x": "620",
    "value": 10.648
  },
  {
    "y": "522",
    "x": "623",
    "value": 11.033
  },
  {
    "y": "522",
    "x": "626",
    "value": 10.184
  },
  {
    "y": "522",
    "x": "628",
    "value": 4.982
  },
  {
    "y": "522",
    "x": "631",
    "value": 0.067
  },
  {
    "y": "522",
    "x": "634",
    "value": 0.036
  },
  {
    "y": "522",
    "x": "636",
    "value": 0.021
  },
  {
    "y": "522",
    "x": "639",
    "value": 0.008
  },
  {
    "y": "527",
    "x": "540",
    "value": 1.581
  },
  {
    "y": "527",
    "x": "542",
    "value": 0.393
  },
  {
    "y": "527",
    "x": "599",
    "value": 0.005
  },
  {
    "y": "527",
    "x": "601",
    "value": 3.341
  },
  {
    "y": "527",
    "x": "604",
    "value": 7.897
  },
  {
    "y": "527",
    "x": "607",
    "value": 9.012
  },
  {
    "y": "527",
    "x": "609",
    "value": 9.867
  },
  {
    "y": "527",
    "x": "612",
    "value": 10.347
  },
  {
    "y": "527",
    "x": "615",
    "value": 10.531
  },
  {
    "y": "527",
    "x": "617",
    "value": 10.673
  },
  {
    "y": "527",
    "x": "620",
    "value": 11.136
  },
  {
    "y": "527",
    "x": "623",
    "value": 11.128
  },
  {
    "y": "527",
    "x": "626",
    "value": 10.026
  },
  {
    "y": "527",
    "x": "628",
    "value": 4.608
  },
  {
    "y": "527",
    "x": "631",
    "value": 0.073
  },
  {
    "y": "527",
    "x": "634",
    "value": 2.398
  },
  {
    "y": "527",
    "x": "636",
    "value": 4.617
  },
  {
    "y": "527",
    "x": "639",
    "value": 4.308
  },
  {
    "y": "527",
    "x": "642",
    "value": 0.04
  },
  {
    "y": "527",
    "x": "644",
    "value": 0.018
  },
  {
    "y": "527",
    "x": "647",
    "value": 0.005
  },
  {
    "y": "527",
    "x": "650",
    "value": 0.001
  },
  {
    "y": "527",
    "x": "658",
    "value": 0.001
  },
  {
    "y": "531",
    "x": "601",
    "value": 0.014
  },
  {
    "y": "531",
    "x": "604",
    "value": 3.744
  },
  {
    "y": "531",
    "x": "607",
    "value": 8.513
  },
  {
    "y": "531",
    "x": "609",
    "value": 9.606
  },
  {
    "y": "531",
    "x": "612",
    "value": 10.094
  },
  {
    "y": "531",
    "x": "615",
    "value": 10.262
  },
  {
    "y": "531",
    "x": "617",
    "value": 10.452
  },
  {
    "y": "531",
    "x": "620",
    "value": 10.678
  },
  {
    "y": "531",
    "x": "623",
    "value": 10.388
  },
  {
    "y": "531",
    "x": "626",
    "value": 7.755
  },
  {
    "y": "531",
    "x": "628",
    "value": 2.317
  },
  {
    "y": "531",
    "x": "631",
    "value": 5.881
  },
  {
    "y": "531",
    "x": "634",
    "value": 10.417
  },
  {
    "y": "531",
    "x": "636",
    "value": 4.657
  },
  {
    "y": "531",
    "x": "639",
    "value": 0.068
  },
  {
    "y": "531",
    "x": "642",
    "value": 0.064
  },
  {
    "y": "531",
    "x": "644",
    "value": 1.677
  },
  {
    "y": "531",
    "x": "647",
    "value": 0.06
  },
  {
    "y": "531",
    "x": "650",
    "value": 0.034
  },
  {
    "y": "531",
    "x": "652",
    "value": 0.023
  },
  {
    "y": "531",
    "x": "655",
    "value": 0.016
  },
  {
    "y": "531",
    "x": "658",
    "value": 0.01
  },
  {
    "y": "535",
    "x": "604",
    "value": 0.032
  },
  {
    "y": "535",
    "x": "607",
    "value": 4.154
  },
  {
    "y": "535",
    "x": "609",
    "value": 9.001
  },
  {
    "y": "535",
    "x": "612",
    "value": 9.434
  },
  {
    "y": "535",
    "x": "615",
    "value": 9.806
  },
  {
    "y": "535",
    "x": "617",
    "value": 10.448
  },
  {
    "y": "535",
    "x": "620",
    "value": 10.697
  },
  {
    "y": "535",
    "x": "623",
    "value": 10.668
  },
  {
    "y": "535",
    "x": "626",
    "value": 6.533
  },
  {
    "y": "535",
    "x": "628",
    "value": 5.93
  },
  {
    "y": "535",
    "x": "631",
    "value": 10.543
  },
  {
    "y": "535",
    "x": "634",
    "value": 6.765
  },
  {
    "y": "535",
    "x": "636",
    "value": 2.025
  },
  {
    "y": "535",
    "x": "639",
    "value": 0.068
  },
  {
    "y": "535",
    "x": "642",
    "value": 4.708
  },
  {
    "y": "535",
    "x": "644",
    "value": 8.433
  },
  {
    "y": "535",
    "x": "647",
    "value": 3.669
  },
  {
    "y": "535",
    "x": "650",
    "value": 0.056
  },
  {
    "y": "535",
    "x": "652",
    "value": 0.046
  },
  {
    "y": "535",
    "x": "655",
    "value": 0.034
  },
  {
    "y": "535",
    "x": "658",
    "value": 0.043
  },
  {
    "y": "535",
    "x": "660",
    "value": 0.039
  },
  {
    "y": "535",
    "x": "663",
    "value": 0.028
  },
  {
    "y": "535",
    "x": "666",
    "value": 0.022
  },
  {
    "y": "535",
    "x": "668",
    "value": 0.014
  },
  {
    "y": "540",
    "x": "604",
    "value": 0.008
  },
  {
    "y": "540",
    "x": "607",
    "value": 0.055
  },
  {
    "y": "540",
    "x": "609",
    "value": 6.89
  },
  {
    "y": "540",
    "x": "612",
    "value": 8.219
  },
  {
    "y": "540",
    "x": "615",
    "value": 8.025
  },
  {
    "y": "540",
    "x": "617",
    "value": 10.247
  },
  {
    "y": "540",
    "x": "620",
    "value": 10.414
  },
  {
    "y": "540",
    "x": "623",
    "value": 10.379
  },
  {
    "y": "540",
    "x": "626",
    "value": 10.367
  },
  {
    "y": "540",
    "x": "628",
    "value": 9.97
  },
  {
    "y": "540",
    "x": "631",
    "value": 9.137
  },
  {
    "y": "540",
    "x": "634",
    "value": 4.283
  },
  {
    "y": "540",
    "x": "636",
    "value": 3.702
  },
  {
    "y": "540",
    "x": "639",
    "value": 7.945
  },
  {
    "y": "540",
    "x": "642",
    "value": 9.942
  },
  {
    "y": "540",
    "x": "644",
    "value": 4.574
  },
  {
    "y": "540",
    "x": "647",
    "value": 0.066
  },
  {
    "y": "540",
    "x": "650",
    "value": 0.075
  },
  {
    "y": "540",
    "x": "652",
    "value": 1.554
  },
  {
    "y": "540",
    "x": "655",
    "value": 0.056
  },
  {
    "y": "540",
    "x": "658",
    "value": 0.043
  },
  {
    "y": "540",
    "x": "660",
    "value": 0.045
  },
  {
    "y": "540",
    "x": "663",
    "value": 0.043
  },
  {
    "y": "540",
    "x": "666",
    "value": 0.037
  },
  {
    "y": "540",
    "x": "668",
    "value": 0.597
  },
  {
    "y": "540",
    "x": "671",
    "value": 1.006
  },
  {
    "y": "540",
    "x": "674",
    "value": 0.488
  },
  {
    "y": "544",
    "x": "534",
    "value": 0.215
  },
  {
    "y": "544",
    "x": "607",
    "value": 0.026
  },
  {
    "y": "544",
    "x": "609",
    "value": 3.814
  },
  {
    "y": "544",
    "x": "612",
    "value": 5.613
  },
  {
    "y": "544",
    "x": "615",
    "value": 5.174
  },
  {
    "y": "544",
    "x": "617",
    "value": 8.708
  },
  {
    "y": "544",
    "x": "620",
    "value": 8.311
  },
  {
    "y": "544",
    "x": "623",
    "value": 8.686
  },
  {
    "y": "544",
    "x": "626",
    "value": 8.991
  },
  {
    "y": "544",
    "x": "628",
    "value": 8.764
  },
  {
    "y": "544",
    "x": "631",
    "value": 8.821
  },
  {
    "y": "544",
    "x": "634",
    "value": 8.838
  },
  {
    "y": "544",
    "x": "636",
    "value": 9.379
  },
  {
    "y": "544",
    "x": "639",
    "value": 8.664
  },
  {
    "y": "544",
    "x": "642",
    "value": 4.863
  },
  {
    "y": "544",
    "x": "644",
    "value": 1.151
  },
  {
    "y": "544",
    "x": "647",
    "value": 1.033
  },
  {
    "y": "544",
    "x": "650",
    "value": 4.416
  },
  {
    "y": "544",
    "x": "652",
    "value": 8.005
  },
  {
    "y": "544",
    "x": "655",
    "value": 3.506
  },
  {
    "y": "544",
    "x": "658",
    "value": 0.164
  },
  {
    "y": "544",
    "x": "660",
    "value": 0.09
  },
  {
    "y": "544",
    "x": "663",
    "value": 0.069
  },
  {
    "y": "544",
    "x": "666",
    "value": 3.877
  },
  {
    "y": "544",
    "x": "668",
    "value": 6.792
  },
  {
    "y": "544",
    "x": "671",
    "value": 5.743
  },
  {
    "y": "544",
    "x": "674",
    "value": 5.81
  },
  {
    "y": "544",
    "x": "677",
    "value": 6.26
  },
  {
    "y": "544",
    "x": "679",
    "value": 6.399
  },
  {
    "y": "544",
    "x": "682",
    "value": 6.351
  },
  {
    "y": "544",
    "x": "685",
    "value": 5.761
  },
  {
    "y": "544",
    "x": "687",
    "value": 2.651
  },
  {
    "y": "544",
    "x": "690",
    "value": 1.782
  },
  {
    "y": "544",
    "x": "693",
    "value": 1.828
  },
  {
    "y": "549",
    "x": "609",
    "value": 0.029
  },
  {
    "y": "549",
    "x": "612",
    "value": 3.359
  },
  {
    "y": "549",
    "x": "615",
    "value": 5.801
  },
  {
    "y": "549",
    "x": "617",
    "value": 6.089
  },
  {
    "y": "549",
    "x": "620",
    "value": 6.421
  },
  {
    "y": "549",
    "x": "623",
    "value": 7.228
  },
  {
    "y": "549",
    "x": "626",
    "value": 7.763
  },
  {
    "y": "549",
    "x": "628",
    "value": 8.18
  },
  {
    "y": "549",
    "x": "631",
    "value": 8.588
  },
  {
    "y": "549",
    "x": "634",
    "value": 8.973
  },
  {
    "y": "549",
    "x": "636",
    "value": 9.21
  },
  {
    "y": "549",
    "x": "639",
    "value": 9.426
  },
  {
    "y": "549",
    "x": "642",
    "value": 9.649
  },
  {
    "y": "549",
    "x": "644",
    "value": 9.86
  },
  {
    "y": "549",
    "x": "647",
    "value": 9.924
  },
  {
    "y": "549",
    "x": "650",
    "value": 9.637
  },
  {
    "y": "549",
    "x": "652",
    "value": 9.387
  },
  {
    "y": "549",
    "x": "655",
    "value": 9.623
  },
  {
    "y": "549",
    "x": "658",
    "value": 10.158
  },
  {
    "y": "549",
    "x": "660",
    "value": 11.039
  },
  {
    "y": "549",
    "x": "663",
    "value": 12.032
  },
  {
    "y": "549",
    "x": "666",
    "value": 12.987
  },
  {
    "y": "549",
    "x": "668",
    "value": 14.165
  },
  {
    "y": "549",
    "x": "671",
    "value": 14.944
  },
  {
    "y": "549",
    "x": "674",
    "value": 14.788
  },
  {
    "y": "549",
    "x": "677",
    "value": 14.287
  },
  {
    "y": "549",
    "x": "679",
    "value": 13.854
  },
  {
    "y": "549",
    "x": "682",
    "value": 13.292
  },
  {
    "y": "549",
    "x": "685",
    "value": 12.434
  },
  {
    "y": "549",
    "x": "687",
    "value": 11.596
  },
  {
    "y": "549",
    "x": "690",
    "value": 10.933
  },
  {
    "y": "549",
    "x": "693",
    "value": 10.47
  },
  {
    "y": "549",
    "x": "695",
    "value": 10.216
  },
  {
    "y": "549",
    "x": "698",
    "value": 9.261
  },
  {
    "y": "549",
    "x": "701",
    "value": 6.053
  },
  {
    "y": "549",
    "x": "703",
    "value": 2.208
  },
  {
    "y": "553",
    "x": "628",
    "value": 2.439
  },
  {
    "y": "553",
    "x": "631",
    "value": 5.194
  },
  {
    "y": "553",
    "x": "634",
    "value": 5.865
  },
  {
    "y": "553",
    "x": "636",
    "value": 6.452
  },
  {
    "y": "553",
    "x": "639",
    "value": 6.841
  },
  {
    "y": "553",
    "x": "642",
    "value": 7.157
  },
  {
    "y": "553",
    "x": "644",
    "value": 8.072
  },
  {
    "y": "553",
    "x": "647",
    "value": 9.05
  },
  {
    "y": "553",
    "x": "650",
    "value": 9.553
  },
  {
    "y": "553",
    "x": "652",
    "value": 9.95
  },
  {
    "y": "553",
    "x": "655",
    "value": 10.179
  },
  {
    "y": "553",
    "x": "658",
    "value": 10.014
  },
  {
    "y": "553",
    "x": "660",
    "value": 9.799
  },
  {
    "y": "553",
    "x": "663",
    "value": 9.64
  },
  {
    "y": "553",
    "x": "666",
    "value": 9.551
  },
  {
    "y": "553",
    "x": "668",
    "value": 9.783
  },
  {
    "y": "553",
    "x": "671",
    "value": 10.061
  },
  {
    "y": "553",
    "x": "674",
    "value": 9.96
  },
  {
    "y": "553",
    "x": "677",
    "value": 9.675
  },
  {
    "y": "553",
    "x": "679",
    "value": 9.751
  },
  {
    "y": "553",
    "x": "682",
    "value": 10.063
  },
  {
    "y": "553",
    "x": "685",
    "value": 10.21
  },
  {
    "y": "553",
    "x": "687",
    "value": 10.31
  },
  {
    "y": "553",
    "x": "690",
    "value": 10.536
  },
  {
    "y": "553",
    "x": "693",
    "value": 10.785
  },
  {
    "y": "553",
    "x": "695",
    "value": 10.968
  },
  {
    "y": "553",
    "x": "698",
    "value": 10.438
  },
  {
    "y": "553",
    "x": "701",
    "value": 8.239
  },
  {
    "y": "553",
    "x": "703",
    "value": 6.299
  },
  {
    "y": "553",
    "x": "706",
    "value": 4.833
  },
  {
    "y": "553",
    "x": "709",
    "value": 2.895
  },
  {
    "y": "558",
    "x": "529",
    "value": 0.074
  },
  {
    "y": "558",
    "x": "663",
    "value": 2.051
  },
  {
    "y": "558",
    "x": "666",
    "value": 3.758
  },
  {
    "y": "558",
    "x": "668",
    "value": 3.855
  },
  {
    "y": "558",
    "x": "671",
    "value": 4.878
  },
  {
    "y": "558",
    "x": "674",
    "value": 5.807
  },
  {
    "y": "558",
    "x": "677",
    "value": 6.635
  },
  {
    "y": "558",
    "x": "679",
    "value": 7.753
  },
  {
    "y": "558",
    "x": "682",
    "value": 8.221
  },
  {
    "y": "558",
    "x": "685",
    "value": 4.099
  },
  {
    "y": "558",
    "x": "687",
    "value": 0.918
  },
  {
    "y": "558",
    "x": "690",
    "value": 4.943
  },
  {
    "y": "558",
    "x": "693",
    "value": 9.436
  },
  {
    "y": "558",
    "x": "695",
    "value": 9.119
  },
  {
    "y": "558",
    "x": "698",
    "value": 8.903
  },
  {
    "y": "558",
    "x": "701",
    "value": 8.01
  },
  {
    "y": "558",
    "x": "703",
    "value": 6.968
  },
  {
    "y": "558",
    "x": "706",
    "value": 6.039
  },
  {
    "y": "558",
    "x": "709",
    "value": 5.295
  },
  {
    "y": "558",
    "x": "711",
    "value": 1.961
  },
  {
    "y": "562",
    "x": "526",
    "value": 0.055
  },
  {
    "y": "562",
    "x": "677",
    "value": 0.168
  },
  {
    "y": "562",
    "x": "679",
    "value": 0.021
  },
  {
    "y": "562",
    "x": "682",
    "value": 1.942
  },
  {
    "y": "562",
    "x": "685",
    "value": 3.785
  },
  {
    "y": "562",
    "x": "687",
    "value": 4.152
  },
  {
    "y": "562",
    "x": "690",
    "value": 2.17
  },
  {
    "y": "562",
    "x": "693",
    "value": 0.049
  },
  {
    "y": "562",
    "x": "695",
    "value": 4.468
  },
  {
    "y": "562",
    "x": "698",
    "value": 8.275
  },
  {
    "y": "562",
    "x": "701",
    "value": 7.688
  },
  {
    "y": "562",
    "x": "703",
    "value": 7.478
  },
  {
    "y": "562",
    "x": "706",
    "value": 6.606
  },
  {
    "y": "562",
    "x": "709",
    "value": 5.694
  },
  {
    "y": "562",
    "x": "711",
    "value": 4.66
  },
  {
    "y": "562",
    "x": "714",
    "value": 2.86
  },
  {
    "y": "562",
    "x": "717",
    "value": 1.572
  },
  {
    "y": "566",
    "x": "523",
    "value": 0.033
  },
  {
    "y": "566",
    "x": "703",
    "value": 2.712
  },
  {
    "y": "566",
    "x": "706",
    "value": 5.43
  },
  {
    "y": "566",
    "x": "709",
    "value": 5.276
  },
  {
    "y": "566",
    "x": "711",
    "value": 4.527
  },
  {
    "y": "566",
    "x": "714",
    "value": 3.157
  },
  {
    "y": "566",
    "x": "717",
    "value": 2.415
  },
  {
    "y": "566",
    "x": "719",
    "value": 0.563
  },
  {
    "y": "566",
    "x": "722",
    "value": 1.663
  },
  {
    "y": "566",
    "x": "725",
    "value": 0.834
  },
  {
    "y": "566",
    "x": "728",
    "value": 0.663
  },
  {
    "y": "571",
    "x": "703",
    "value": 0.003
  },
  {
    "y": "571",
    "x": "706",
    "value": 2.319
  },
  {
    "y": "571",
    "x": "709",
    "value": 4.508
  },
  {
    "y": "571",
    "x": "711",
    "value": 3.689
  },
  {
    "y": "571",
    "x": "714",
    "value": 2.658
  },
  {
    "y": "571",
    "x": "717",
    "value": 2.179
  },
  {
    "y": "571",
    "x": "719",
    "value": 1.849
  },
  {
    "y": "571",
    "x": "722",
    "value": 0.765
  },
  {
    "y": "571",
    "x": "725",
    "value": 0.146
  },
  {
    "y": "571",
    "x": "728",
    "value": 1.039
  },
  {
    "y": "575",
    "x": "709",
    "value": 1.547
  },
  {
    "y": "575",
    "x": "711",
    "value": 2.524
  },
  {
    "y": "575",
    "x": "714",
    "value": 2.05
  },
  {
    "y": "575",
    "x": "717",
    "value": 2.067
  },
  {
    "y": "575",
    "x": "719",
    "value": 2.389
  },
  {
    "y": "575",
    "x": "722",
    "value": 3.025
  },
  {
    "y": "575",
    "x": "725",
    "value": 3.1
  },
  {
    "y": "575",
    "x": "728",
    "value": 3.701
  },
  {
    "y": "575",
    "x": "730",
    "value": 3.83
  },
  {
    "y": "575",
    "x": "733",
    "value": 3.703
  },
  {
    "y": "575",
    "x": "736",
    "value": 3.286
  },
  {
    "y": "575",
    "x": "738",
    "value": 1.829
  },
  {
    "y": "580",
    "x": "711",
    "value": 0.957
  },
  {
    "y": "580",
    "x": "714",
    "value": 1.275
  },
  {
    "y": "580",
    "x": "717",
    "value": 1.873
  },
  {
    "y": "580",
    "x": "719",
    "value": 2.444
  },
  {
    "y": "580",
    "x": "722",
    "value": 2.937
  },
  {
    "y": "580",
    "x": "725",
    "value": 3.737
  },
  {
    "y": "580",
    "x": "728",
    "value": 4.466
  },
  {
    "y": "580",
    "x": "730",
    "value": 4.736
  },
  {
    "y": "580",
    "x": "733",
    "value": 4.82
  },
  {
    "y": "580",
    "x": "736",
    "value": 4.97
  },
  {
    "y": "580",
    "x": "738",
    "value": 5.2
  },
  {
    "y": "580",
    "x": "741",
    "value": 3.95
  },
  {
    "y": "580",
    "x": "744",
    "value": 2.277
  },
  {
    "y": "584",
    "x": "711",
    "value": 0.491
  },
  {
    "y": "584",
    "x": "714",
    "value": 1.378
  },
  {
    "y": "584",
    "x": "717",
    "value": 2.178
  },
  {
    "y": "584",
    "x": "719",
    "value": 2.587
  },
  {
    "y": "584",
    "x": "722",
    "value": 3.102
  },
  {
    "y": "584",
    "x": "725",
    "value": 4.12
  },
  {
    "y": "584",
    "x": "728",
    "value": 5.132
  },
  {
    "y": "584",
    "x": "730",
    "value": 5.658
  },
  {
    "y": "584",
    "x": "733",
    "value": 5.636
  },
  {
    "y": "584",
    "x": "736",
    "value": 5.61
  },
  {
    "y": "584",
    "x": "738",
    "value": 5.591
  },
  {
    "y": "584",
    "x": "741",
    "value": 5.133
  },
  {
    "y": "584",
    "x": "744",
    "value": 5.224
  },
  {
    "y": "584",
    "x": "746",
    "value": 3.937
  },
  {
    "y": "584",
    "x": "749",
    "value": 2.317
  },
  {
    "y": "588",
    "x": "722",
    "value": 1.547
  },
  {
    "y": "588",
    "x": "725",
    "value": 3.323
  },
  {
    "y": "588",
    "x": "728",
    "value": 3.672
  },
  {
    "y": "588",
    "x": "730",
    "value": 4.261
  },
  {
    "y": "588",
    "x": "733",
    "value": 5.212
  },
  {
    "y": "588",
    "x": "736",
    "value": 5.498
  },
  {
    "y": "588",
    "x": "738",
    "value": 5.541
  },
  {
    "y": "588",
    "x": "741",
    "value": 5.852
  },
  {
    "y": "588",
    "x": "744",
    "value": 6.401
  },
  {
    "y": "588",
    "x": "746",
    "value": 5.887
  },
  {
    "y": "588",
    "x": "749",
    "value": 4.882
  },
  {
    "y": "588",
    "x": "752",
    "value": 1.991
  },
  {
    "y": "593",
    "x": "733",
    "value": 1.795
  },
  {
    "y": "593",
    "x": "736",
    "value": 3.889
  },
  {
    "y": "593",
    "x": "738",
    "value": 5.143
  },
  {
    "y": "593",
    "x": "741",
    "value": 6.036
  },
  {
    "y": "593",
    "x": "744",
    "value": 6.235
  },
  {
    "y": "593",
    "x": "746",
    "value": 5.763
  },
  {
    "y": "593",
    "x": "749",
    "value": 5.37
  },
  {
    "y": "593",
    "x": "752",
    "value": 4.971
  },
  {
    "y": "593",
    "x": "754",
    "value": 3.673
  },
  {
    "y": "593",
    "x": "757",
    "value": 1.683
  },
  {
    "y": "597",
    "x": "738",
    "value": 2.448
  },
  {
    "y": "597",
    "x": "741",
    "value": 5.35
  },
  {
    "y": "597",
    "x": "744",
    "value": 5.267
  },
  {
    "y": "597",
    "x": "746",
    "value": 5.034
  },
  {
    "y": "597",
    "x": "749",
    "value": 5.124
  },
  {
    "y": "597",
    "x": "752",
    "value": 5.513
  },
  {
    "y": "597",
    "x": "754",
    "value": 4.968
  },
  {
    "y": "597",
    "x": "757",
    "value": 3.818
  },
  {
    "y": "597",
    "x": "760",
    "value": 2.396
  },
  {
    "y": "597",
    "x": "762",
    "value": 1.355
  },
  {
    "y": "602",
    "x": "738",
    "value": 0.452
  },
  {
    "y": "602",
    "x": "741",
    "value": 2.353
  },
  {
    "y": "602",
    "x": "744",
    "value": 4.21
  },
  {
    "y": "602",
    "x": "746",
    "value": 4.73
  },
  {
    "y": "602",
    "x": "749",
    "value": 5.287
  },
  {
    "y": "602",
    "x": "752",
    "value": 5.918
  },
  {
    "y": "602",
    "x": "754",
    "value": 5.633
  },
  {
    "y": "602",
    "x": "757",
    "value": 4.922
  },
  {
    "y": "602",
    "x": "760",
    "value": 4.011
  },
  {
    "y": "602",
    "x": "762",
    "value": 3.694
  },
  {
    "y": "602",
    "x": "765",
    "value": 3.418
  },
  {
    "y": "602",
    "x": "768",
    "value": 3.955
  },
  {
    "y": "602",
    "x": "770",
    "value": 3.939
  },
  {
    "y": "602",
    "x": "773",
    "value": 2.161
  },
  {
    "y": "606",
    "x": "744",
    "value": 3.09
  },
  {
    "y": "606",
    "x": "746",
    "value": 4.59
  },
  {
    "y": "606",
    "x": "749",
    "value": 5.467
  },
  {
    "y": "606",
    "x": "752",
    "value": 5.915
  },
  {
    "y": "606",
    "x": "754",
    "value": 5.494
  },
  {
    "y": "606",
    "x": "757",
    "value": 4.905
  },
  {
    "y": "606",
    "x": "760",
    "value": 4.482
  },
  {
    "y": "606",
    "x": "762",
    "value": 4.757
  },
  {
    "y": "606",
    "x": "765",
    "value": 4.818
  },
  {
    "y": "606",
    "x": "768",
    "value": 5.105
  },
  {
    "y": "606",
    "x": "770",
    "value": 4.986
  },
  {
    "y": "606",
    "x": "773",
    "value": 3.855
  },
  {
    "y": "606",
    "x": "776",
    "value": 2.626
  },
  {
    "y": "606",
    "x": "779",
    "value": 1.037
  },
  {
    "y": "611",
    "x": "744",
    "value": 1.706
  },
  {
    "y": "611",
    "x": "746",
    "value": 4.102
  },
  {
    "y": "611",
    "x": "749",
    "value": 4.957
  },
  {
    "y": "611",
    "x": "752",
    "value": 5.019
  },
  {
    "y": "611",
    "x": "754",
    "value": 4.29
  },
  {
    "y": "611",
    "x": "757",
    "value": 4.213
  },
  {
    "y": "611",
    "x": "760",
    "value": 4.829
  },
  {
    "y": "611",
    "x": "762",
    "value": 5.275
  },
  {
    "y": "611",
    "x": "765",
    "value": 5.205
  },
  {
    "y": "611",
    "x": "768",
    "value": 5.104
  },
  {
    "y": "611",
    "x": "770",
    "value": 3.354
  },
  {
    "y": "611",
    "x": "773",
    "value": 1.609
  },
  {
    "y": "611",
    "x": "776",
    "value": 1.533
  },
  {
    "y": "611",
    "x": "779",
    "value": 1.064
  },
  {
    "y": "611",
    "x": "781",
    "value": 0.713
  },
  {
    "y": "615",
    "x": "746",
    "value": 1.754
  },
  {
    "y": "615",
    "x": "749",
    "value": 3.122
  },
  {
    "y": "615",
    "x": "752",
    "value": 3.816
  },
  {
    "y": "615",
    "x": "754",
    "value": 3.729
  },
  {
    "y": "615",
    "x": "757",
    "value": 4.411
  },
  {
    "y": "615",
    "x": "760",
    "value": 5.145
  },
  {
    "y": "615",
    "x": "762",
    "value": 5.243
  },
  {
    "y": "615",
    "x": "765",
    "value": 5.252
  },
  {
    "y": "615",
    "x": "768",
    "value": 5.084
  },
  {
    "y": "615",
    "x": "770",
    "value": 4.58
  },
  {
    "y": "615",
    "x": "773",
    "value": 3.58
  },
  {
    "y": "615",
    "x": "776",
    "value": 2.461
  },
  {
    "y": "615",
    "x": "779",
    "value": 1.507
  },
  {
    "y": "615",
    "x": "781",
    "value": 0.274
  },
  {
    "y": "615",
    "x": "784",
    "value": 0.424
  },
  {
    "y": "619",
    "x": "752",
    "value": 1.201
  },
  {
    "y": "619",
    "x": "754",
    "value": 3.022
  },
  {
    "y": "619",
    "x": "757",
    "value": 4.307
  },
  {
    "y": "619",
    "x": "760",
    "value": 4.424
  },
  {
    "y": "619",
    "x": "762",
    "value": 4.355
  },
  {
    "y": "619",
    "x": "765",
    "value": 4.634
  },
  {
    "y": "619",
    "x": "768",
    "value": 4.607
  },
  {
    "y": "619",
    "x": "770",
    "value": 4.604
  },
  {
    "y": "619",
    "x": "773",
    "value": 4.746
  },
  {
    "y": "619",
    "x": "776",
    "value": 4.607
  },
  {
    "y": "619",
    "x": "779",
    "value": 4.296
  },
  {
    "y": "619",
    "x": "781",
    "value": 4.237
  },
  {
    "y": "619",
    "x": "784",
    "value": 3.667
  },
  {
    "y": "619",
    "x": "787",
    "value": 1.84
  },
  {
    "y": "624",
    "x": "754",
    "value": 1.571
  },
  {
    "y": "624",
    "x": "757",
    "value": 3.141
  },
  {
    "y": "624",
    "x": "760",
    "value": 3.622
  },
  {
    "y": "624",
    "x": "762",
    "value": 4.498
  },
  {
    "y": "624",
    "x": "765",
    "value": 5.082
  },
  {
    "y": "624",
    "x": "768",
    "value": 5.539
  },
  {
    "y": "624",
    "x": "770",
    "value": 6.31
  },
  {
    "y": "624",
    "x": "773",
    "value": 6.703
  },
  {
    "y": "624",
    "x": "776",
    "value": 6.145
  },
  {
    "y": "624",
    "x": "779",
    "value": 5.292
  },
  {
    "y": "624",
    "x": "781",
    "value": 4.793
  },
  {
    "y": "624",
    "x": "784",
    "value": 4.38
  },
  {
    "y": "624",
    "x": "787",
    "value": 4.132
  },
  {
    "y": "624",
    "x": "789",
    "value": 3.154
  },
  {
    "y": "624",
    "x": "792",
    "value": 1.876
  },
  {
    "y": "628",
    "x": "770",
    "value": 0.27
  },
  {
    "y": "628",
    "x": "773",
    "value": 2.851
  },
  {
    "y": "628",
    "x": "776",
    "value": 5.034
  },
  {
    "y": "628",
    "x": "779",
    "value": 4.337
  },
  {
    "y": "628",
    "x": "781",
    "value": 4.191
  },
  {
    "y": "628",
    "x": "784",
    "value": 4.226
  },
  {
    "y": "628",
    "x": "787",
    "value": 4.616
  },
  {
    "y": "628",
    "x": "789",
    "value": 4.515
  },
  {
    "y": "628",
    "x": "792",
    "value": 4.494
  },
  {
    "y": "628",
    "x": "795",
    "value": 1.715
  },
  {
    "y": "633",
    "x": "779",
    "value": 1.995
  },
  {
    "y": "633",
    "x": "781",
    "value": 3.638
  },
  {
    "y": "633",
    "x": "784",
    "value": 4.263
  },
  {
    "y": "633",
    "x": "787",
    "value": 5.032
  },
  {
    "y": "633",
    "x": "789",
    "value": 5.064
  },
  {
    "y": "633",
    "x": "792",
    "value": 4.498
  },
  {
    "y": "633",
    "x": "795",
    "value": 2.92
  },
  {
    "y": "637",
    "x": "779",
    "value": 1.208
  },
  {
    "y": "637",
    "x": "781",
    "value": 3.232
  },
  {
    "y": "637",
    "x": "784",
    "value": 4.243
  },
  {
    "y": "637",
    "x": "787",
    "value": 4.922
  },
  {
    "y": "637",
    "x": "789",
    "value": 4.583
  },
  {
    "y": "637",
    "x": "792",
    "value": 4.044
  },
  {
    "y": "637",
    "x": "795",
    "value": 3.868
  },
  {
    "y": "637",
    "x": "797",
    "value": 1.483
  },
  {
    "y": "642",
    "x": "781",
    "value": 1.545
  },
  {
    "y": "642",
    "x": "784",
    "value": 3.668
  },
  {
    "y": "642",
    "x": "787",
    "value": 4.241
  },
  {
    "y": "642",
    "x": "789",
    "value": 4.018
  },
  {
    "y": "642",
    "x": "792",
    "value": 3.836
  },
  {
    "y": "642",
    "x": "795",
    "value": 4.047
  },
  {
    "y": "642",
    "x": "797",
    "value": 3.107
  },
  {
    "y": "642",
    "x": "800",
    "value": 1.028
  },
  {
    "y": "646",
    "x": "784",
    "value": 1.494
  },
  {
    "y": "646",
    "x": "787",
    "value": 3.21
  },
  {
    "y": "646",
    "x": "789",
    "value": 3.547
  },
  {
    "y": "646",
    "x": "792",
    "value": 3.709
  },
  {
    "y": "646",
    "x": "795",
    "value": 3.962
  },
  {
    "y": "646",
    "x": "797",
    "value": 3.514
  },
  {
    "y": "646",
    "x": "800",
    "value": 3.111
  },
  {
    "y": "646",
    "x": "803",
    "value": 2.332
  },
  {
    "y": "646",
    "x": "805",
    "value": 1.166
  },
  {
    "y": "650",
    "x": "787",
    "value": 1.447
  },
  {
    "y": "650",
    "x": "789",
    "value": 3.332
  },
  {
    "y": "650",
    "x": "792",
    "value": 4.041
  },
  {
    "y": "650",
    "x": "795",
    "value": 4.204
  },
  {
    "y": "650",
    "x": "797",
    "value": 4.021
  },
  {
    "y": "650",
    "x": "800",
    "value": 3.969
  },
  {
    "y": "650",
    "x": "803",
    "value": 3.344
  },
  {
    "y": "650",
    "x": "805",
    "value": 2.443
  },
  {
    "y": "655",
    "x": "789",
    "value": 1.772
  },
  {
    "y": "655",
    "x": "792",
    "value": 4.053
  },
  {
    "y": "655",
    "x": "795",
    "value": 4.207
  },
  {
    "y": "655",
    "x": "797",
    "value": 4.313
  },
  {
    "y": "655",
    "x": "800",
    "value": 4.548
  },
  {
    "y": "655",
    "x": "803",
    "value": 4.112
  },
  {
    "y": "655",
    "x": "805",
    "value": 3.792
  },
  {
    "y": "655",
    "x": "808",
    "value": 1.611
  },
  {
    "y": "655",
    "x": "811",
    "value": 0.01
  },
  {
    "y": "655",
    "x": "813",
    "value": 0.001
  },
  {
    "y": "659",
    "x": "789",
    "value": 0.003
  },
  {
    "y": "659",
    "x": "792",
    "value": 1.864
  },
  {
    "y": "659",
    "x": "795",
    "value": 4.196
  },
  {
    "y": "659",
    "x": "797",
    "value": 4.674
  },
  {
    "y": "659",
    "x": "800",
    "value": 4.789
  },
  {
    "y": "659",
    "x": "803",
    "value": 4.463
  },
  {
    "y": "659",
    "x": "805",
    "value": 4.591
  },
  {
    "y": "659",
    "x": "808",
    "value": 4.215
  },
  {
    "y": "659",
    "x": "811",
    "value": 2.075
  },
  {
    "y": "659",
    "x": "813",
    "value": 0.022
  },
  {
    "y": "659",
    "x": "816",
    "value": 0.011
  },
  {
    "y": "664",
    "x": "795",
    "value": 3.372
  },
  {
    "y": "664",
    "x": "797",
    "value": 4.558
  },
  {
    "y": "664",
    "x": "800",
    "value": 4.675
  },
  {
    "y": "664",
    "x": "803",
    "value": 4.748
  },
  {
    "y": "664",
    "x": "805",
    "value": 5.249
  },
  {
    "y": "664",
    "x": "808",
    "value": 5.084
  },
  {
    "y": "664",
    "x": "811",
    "value": 4.879
  },
  {
    "y": "664",
    "x": "813",
    "value": 2.317
  },
  {
    "y": "664",
    "x": "816",
    "value": 1.485
  },
  {
    "y": "668",
    "x": "795",
    "value": 1.959
  },
  {
    "y": "668",
    "x": "797",
    "value": 4.667
  },
  {
    "y": "668",
    "x": "800",
    "value": 4.943
  },
  {
    "y": "668",
    "x": "803",
    "value": 5.286
  },
  {
    "y": "668",
    "x": "805",
    "value": 5.797
  },
  {
    "y": "668",
    "x": "808",
    "value": 5.619
  },
  {
    "y": "668",
    "x": "811",
    "value": 5.335
  },
  {
    "y": "668",
    "x": "813",
    "value": 4.27
  },
  {
    "y": "668",
    "x": "816",
    "value": 3.244
  },
  {
    "y": "668",
    "x": "819",
    "value": 0.013
  },
  {
    "y": "668",
    "x": "821",
    "value": 0.002
  },
  {
    "y": "673",
    "x": "795",
    "value": 0.011
  },
  {
    "y": "673",
    "x": "797",
    "value": 4.582
  },
  {
    "y": "673",
    "x": "800",
    "value": 4.958
  },
  {
    "y": "673",
    "x": "803",
    "value": 5.4
  },
  {
    "y": "673",
    "x": "805",
    "value": 5.822
  },
  {
    "y": "673",
    "x": "808",
    "value": 5.576
  },
  {
    "y": "673",
    "x": "811",
    "value": 5.023
  },
  {
    "y": "673",
    "x": "813",
    "value": 4.498
  },
  {
    "y": "673",
    "x": "816",
    "value": 4.41
  },
  {
    "y": "673",
    "x": "819",
    "value": 2.154
  },
  {
    "y": "673",
    "x": "821",
    "value": 0.014
  },
  {
    "y": "677",
    "x": "797",
    "value": 4.802
  },
  {
    "y": "677",
    "x": "800",
    "value": 4.731
  },
  {
    "y": "677",
    "x": "803",
    "value": 4.833
  },
  {
    "y": "677",
    "x": "805",
    "value": 4.741
  },
  {
    "y": "677",
    "x": "808",
    "value": 4.5
  },
  {
    "y": "677",
    "x": "811",
    "value": 4.273
  },
  {
    "y": "677",
    "x": "813",
    "value": 4.308
  },
  {
    "y": "677",
    "x": "816",
    "value": 4.426
  },
  {
    "y": "677",
    "x": "819",
    "value": 4.096
  },
  {
    "y": "677",
    "x": "821",
    "value": 1.763
  },
  {
    "y": "677",
    "x": "824",
    "value": 0.99
  },
  {
    "y": "677",
    "x": "827",
    "value": 0.006
  },
  {
    "y": "677",
    "x": "830",
    "value": 0.005
  },
  {
    "y": "677",
    "x": "832",
    "value": 0.102
  },
  {
    "y": "681",
    "x": "797",
    "value": 3.566
  },
  {
    "y": "681",
    "x": "800",
    "value": 3.664
  },
  {
    "y": "681",
    "x": "803",
    "value": 3.213
  },
  {
    "y": "681",
    "x": "805",
    "value": 2.784
  },
  {
    "y": "681",
    "x": "808",
    "value": 2.876
  },
  {
    "y": "681",
    "x": "811",
    "value": 3.336
  },
  {
    "y": "681",
    "x": "813",
    "value": 4.076
  },
  {
    "y": "681",
    "x": "816",
    "value": 4.474
  },
  {
    "y": "681",
    "x": "819",
    "value": 4.31
  },
  {
    "y": "681",
    "x": "821",
    "value": 4.367
  },
  {
    "y": "681",
    "x": "824",
    "value": 4.938
  },
  {
    "y": "681",
    "x": "827",
    "value": 5.08
  },
  {
    "y": "681",
    "x": "830",
    "value": 4.621
  },
  {
    "y": "681",
    "x": "832",
    "value": 2.126
  },
  {
    "y": "681",
    "x": "835",
    "value": 0.717
  },
  {
    "y": "681",
    "x": "838",
    "value": 0.009
  },
  {
    "y": "681",
    "x": "840",
    "value": 0.001
  },
  {
    "y": "686",
    "x": "797",
    "value": 0.842
  },
  {
    "y": "686",
    "x": "800",
    "value": 1.779
  },
  {
    "y": "686",
    "x": "803",
    "value": 1.341
  },
  {
    "y": "686",
    "x": "805",
    "value": 1.386
  },
  {
    "y": "686",
    "x": "808",
    "value": 2.087
  },
  {
    "y": "686",
    "x": "811",
    "value": 3.173
  },
  {
    "y": "686",
    "x": "813",
    "value": 4.403
  },
  {
    "y": "686",
    "x": "816",
    "value": 4.859
  },
  {
    "y": "686",
    "x": "819",
    "value": 4.702
  },
  {
    "y": "686",
    "x": "821",
    "value": 5.091
  },
  {
    "y": "686",
    "x": "824",
    "value": 5.484
  },
  {
    "y": "686",
    "x": "827",
    "value": 5.449
  },
  {
    "y": "686",
    "x": "830",
    "value": 5.14
  },
  {
    "y": "686",
    "x": "832",
    "value": 5.054
  },
  {
    "y": "686",
    "x": "835",
    "value": 5.411
  },
  {
    "y": "686",
    "x": "838",
    "value": 5.522
  },
  {
    "y": "686",
    "x": "840",
    "value": 2.844
  },
  {
    "y": "686",
    "x": "843",
    "value": 0.061
  },
  {
    "y": "686",
    "x": "846",
    "value": 0.554
  },
  {
    "y": "686",
    "x": "848",
    "value": 0.051
  },
  {
    "y": "686",
    "x": "851",
    "value": 1.079
  },
  {
    "y": "690",
    "x": "797",
    "value": 0.414
  },
  {
    "y": "690",
    "x": "800",
    "value": 0.418
  },
  {
    "y": "690",
    "x": "803",
    "value": 0.686
  },
  {
    "y": "690",
    "x": "805",
    "value": 1.059
  },
  {
    "y": "690",
    "x": "808",
    "value": 1.85
  },
  {
    "y": "690",
    "x": "811",
    "value": 2.99
  },
  {
    "y": "690",
    "x": "813",
    "value": 4.388
  },
  {
    "y": "690",
    "x": "816",
    "value": 5.17
  },
  {
    "y": "690",
    "x": "819",
    "value": 5.361
  },
  {
    "y": "690",
    "x": "821",
    "value": 5.547
  },
  {
    "y": "690",
    "x": "824",
    "value": 5.612
  },
  {
    "y": "690",
    "x": "827",
    "value": 5.555
  },
  {
    "y": "690",
    "x": "830",
    "value": 5.494
  },
  {
    "y": "690",
    "x": "832",
    "value": 5.626
  },
  {
    "y": "690",
    "x": "835",
    "value": 5.872
  },
  {
    "y": "690",
    "x": "838",
    "value": 6.053
  },
  {
    "y": "690",
    "x": "840",
    "value": 6.195
  },
  {
    "y": "690",
    "x": "843",
    "value": 6.512
  },
  {
    "y": "690",
    "x": "846",
    "value": 6.963
  },
  {
    "y": "690",
    "x": "848",
    "value": 6.562
  },
  {
    "y": "690",
    "x": "851",
    "value": 5.673
  },
  {
    "y": "690",
    "x": "854",
    "value": 3.577
  },
  {
    "y": "690",
    "x": "856",
    "value": 1.122
  },
  {
    "y": "695",
    "x": "803",
    "value": 0.199
  },
  {
    "y": "695",
    "x": "805",
    "value": 0.713
  },
  {
    "y": "695",
    "x": "808",
    "value": 1.814
  },
  {
    "y": "695",
    "x": "811",
    "value": 3.265
  },
  {
    "y": "695",
    "x": "813",
    "value": 4.205
  },
  {
    "y": "695",
    "x": "816",
    "value": 4.461
  },
  {
    "y": "695",
    "x": "819",
    "value": 4.965
  },
  {
    "y": "695",
    "x": "821",
    "value": 5.722
  },
  {
    "y": "695",
    "x": "824",
    "value": 5.942
  },
  {
    "y": "695",
    "x": "827",
    "value": 6.117
  },
  {
    "y": "695",
    "x": "830",
    "value": 6.376
  },
  {
    "y": "695",
    "x": "832",
    "value": 6.334
  },
  {
    "y": "695",
    "x": "835",
    "value": 6.006
  },
  {
    "y": "695",
    "x": "838",
    "value": 5.713
  },
  {
    "y": "695",
    "x": "840",
    "value": 5.882
  },
  {
    "y": "695",
    "x": "843",
    "value": 6.34
  },
  {
    "y": "695",
    "x": "846",
    "value": 6.737
  },
  {
    "y": "695",
    "x": "848",
    "value": 7.07
  },
  {
    "y": "695",
    "x": "851",
    "value": 6.903
  },
  {
    "y": "695",
    "x": "854",
    "value": 6.072
  },
  {
    "y": "695",
    "x": "856",
    "value": 4.153
  },
  {
    "y": "695",
    "x": "859",
    "value": 1.867
  },
  {
    "y": "699",
    "x": "813",
    "value": 0.169
  },
  {
    "y": "699",
    "x": "816",
    "value": 0.43
  },
  {
    "y": "699",
    "x": "819",
    "value": 0.243
  },
  {
    "y": "699",
    "x": "821",
    "value": 0.135
  },
  {
    "y": "699",
    "x": "824",
    "value": 0.192
  },
  {
    "y": "699",
    "x": "827",
    "value": 3.437
  },
  {
    "y": "699",
    "x": "830",
    "value": 6.203
  },
  {
    "y": "699",
    "x": "832",
    "value": 5.566
  },
  {
    "y": "699",
    "x": "835",
    "value": 5.319
  },
  {
    "y": "699",
    "x": "838",
    "value": 5.295
  },
  {
    "y": "699",
    "x": "840",
    "value": 5.621
  },
  {
    "y": "699",
    "x": "843",
    "value": 5.981
  },
  {
    "y": "699",
    "x": "846",
    "value": 6.411
  },
  {
    "y": "699",
    "x": "848",
    "value": 6.962
  },
  {
    "y": "699",
    "x": "851",
    "value": 7.431
  },
  {
    "y": "699",
    "x": "854",
    "value": 7.327
  },
  {
    "y": "699",
    "x": "856",
    "value": 6.304
  },
  {
    "y": "699",
    "x": "859",
    "value": 4.92
  },
  {
    "y": "699",
    "x": "862",
    "value": 2.782
  },
  {
    "y": "699",
    "x": "864",
    "value": 1.114
  },
  {
    "y": "704",
    "x": "819",
    "value": 0.006
  },
  {
    "y": "704",
    "x": "832",
    "value": 1.652
  },
  {
    "y": "704",
    "x": "835",
    "value": 3.315
  },
  {
    "y": "704",
    "x": "838",
    "value": 4.171
  },
  {
    "y": "704",
    "x": "840",
    "value": 4.8
  },
  {
    "y": "704",
    "x": "843",
    "value": 5.438
  },
  {
    "y": "704",
    "x": "846",
    "value": 6.126
  },
  {
    "y": "704",
    "x": "848",
    "value": 6.773
  },
  {
    "y": "704",
    "x": "851",
    "value": 7.331
  },
  {
    "y": "704",
    "x": "854",
    "value": 7.635
  },
  {
    "y": "704",
    "x": "856",
    "value": 7.211
  },
  {
    "y": "704",
    "x": "859",
    "value": 5.87
  },
  {
    "y": "704",
    "x": "862",
    "value": 4.079
  },
  {
    "y": "704",
    "x": "864",
    "value": 3.479
  },
  {
    "y": "704",
    "x": "867",
    "value": 3.126
  },
  {
    "y": "704",
    "x": "870",
    "value": 2.706
  },
  {
    "y": "704",
    "x": "872",
    "value": 1.343
  },
  {
    "y": "708",
    "x": "835",
    "value": 0.014
  },
  {
    "y": "708",
    "x": "838",
    "value": 1.89
  },
  {
    "y": "708",
    "x": "840",
    "value": 4.279
  },
  {
    "y": "708",
    "x": "843",
    "value": 5.177
  },
  {
    "y": "708",
    "x": "846",
    "value": 6.063
  },
  {
    "y": "708",
    "x": "848",
    "value": 6.608
  },
  {
    "y": "708",
    "x": "851",
    "value": 6.889
  },
  {
    "y": "708",
    "x": "854",
    "value": 7.164
  },
  {
    "y": "708",
    "x": "856",
    "value": 7.087
  },
  {
    "y": "708",
    "x": "859",
    "value": 6.316
  },
  {
    "y": "708",
    "x": "862",
    "value": 4.956
  },
  {
    "y": "708",
    "x": "864",
    "value": 4.294
  },
  {
    "y": "708",
    "x": "867",
    "value": 4.016
  },
  {
    "y": "708",
    "x": "870",
    "value": 3.581
  },
  {
    "y": "708",
    "x": "872",
    "value": 3.001
  },
  {
    "y": "708",
    "x": "875",
    "value": 2.815
  },
  {
    "y": "708",
    "x": "878",
    "value": 3.788
  },
  {
    "y": "708",
    "x": "881",
    "value": 3.945
  },
  {
    "y": "708",
    "x": "883",
    "value": 2.636
  },
  {
    "y": "708",
    "x": "886",
    "value": 1.002
  },
  {
    "y": "712",
    "x": "835",
    "value": 0.002
  },
  {
    "y": "712",
    "x": "838",
    "value": 0.018
  },
  {
    "y": "712",
    "x": "840",
    "value": 2.106
  },
  {
    "y": "712",
    "x": "843",
    "value": 4.039
  },
  {
    "y": "712",
    "x": "846",
    "value": 5.51
  },
  {
    "y": "712",
    "x": "848",
    "value": 5.983
  },
  {
    "y": "712",
    "x": "851",
    "value": 6.191
  },
  {
    "y": "712",
    "x": "854",
    "value": 6.219
  },
  {
    "y": "712",
    "x": "856",
    "value": 5.869
  },
  {
    "y": "712",
    "x": "859",
    "value": 5.918
  },
  {
    "y": "712",
    "x": "862",
    "value": 5.957
  },
  {
    "y": "712",
    "x": "864",
    "value": 5.623
  },
  {
    "y": "712",
    "x": "867",
    "value": 5.011
  },
  {
    "y": "712",
    "x": "870",
    "value": 3.972
  },
  {
    "y": "712",
    "x": "872",
    "value": 2.989
  },
  {
    "y": "712",
    "x": "875",
    "value": 3.18
  },
  {
    "y": "712",
    "x": "878",
    "value": 4.456
  },
  {
    "y": "712",
    "x": "881",
    "value": 3.854
  },
  {
    "y": "712",
    "x": "883",
    "value": 1.75
  },
  {
    "y": "712",
    "x": "886",
    "value": 1.058
  },
  {
    "y": "712",
    "x": "889",
    "value": 0.264
  },
  {
    "y": "717",
    "x": "838",
    "value": 0.008
  },
  {
    "y": "717",
    "x": "840",
    "value": 0.019
  },
  {
    "y": "717",
    "x": "843",
    "value": 0.035
  },
  {
    "y": "717",
    "x": "846",
    "value": 2.654
  },
  {
    "y": "717",
    "x": "848",
    "value": 5.287
  },
  {
    "y": "717",
    "x": "851",
    "value": 5.124
  },
  {
    "y": "717",
    "x": "854",
    "value": 2.895
  },
  {
    "y": "717",
    "x": "856",
    "value": 0.048
  },
  {
    "y": "717",
    "x": "859",
    "value": 1.642
  },
  {
    "y": "717",
    "x": "862",
    "value": 3.657
  },
  {
    "y": "717",
    "x": "864",
    "value": 5.794
  },
  {
    "y": "717",
    "x": "867",
    "value": 5.294
  },
  {
    "y": "717",
    "x": "870",
    "value": 3.942
  },
  {
    "y": "717",
    "x": "872",
    "value": 2.828
  },
  {
    "y": "717",
    "x": "875",
    "value": 3.255
  },
  {
    "y": "717",
    "x": "878",
    "value": 4.395
  },
  {
    "y": "717",
    "x": "881",
    "value": 3.658
  },
  {
    "y": "717",
    "x": "883",
    "value": 1.882
  },
  {
    "y": "717",
    "x": "886",
    "value": 1.1
  },
  {
    "y": "717",
    "x": "889",
    "value": 0.63
  },
  {
    "y": "721",
    "x": "838",
    "value": 0.005
  },
  {
    "y": "721",
    "x": "840",
    "value": 0.011
  },
  {
    "y": "721",
    "x": "843",
    "value": 0.016
  },
  {
    "y": "721",
    "x": "846",
    "value": 0.026
  },
  {
    "y": "721",
    "x": "848",
    "value": 2.134
  },
  {
    "y": "721",
    "x": "851",
    "value": 2.053
  },
  {
    "y": "721",
    "x": "854",
    "value": 0.726
  },
  {
    "y": "721",
    "x": "856",
    "value": 3.223
  },
  {
    "y": "721",
    "x": "859",
    "value": 5.674
  },
  {
    "y": "721",
    "x": "862",
    "value": 3.126
  },
  {
    "y": "721",
    "x": "864",
    "value": 0.049
  },
  {
    "y": "721",
    "x": "867",
    "value": 2.823
  },
  {
    "y": "721",
    "x": "870",
    "value": 4.713
  },
  {
    "y": "721",
    "x": "872",
    "value": 3.626
  },
  {
    "y": "721",
    "x": "875",
    "value": 4.302
  },
  {
    "y": "721",
    "x": "878",
    "value": 5.155
  },
  {
    "y": "721",
    "x": "881",
    "value": 3.526
  },
  {
    "y": "721",
    "x": "883",
    "value": 1.176
  },
  {
    "y": "721",
    "x": "886",
    "value": 0.861
  },
  {
    "y": "721",
    "x": "889",
    "value": 0.817
  },
  {
    "y": "726",
    "x": "838",
    "value": 0.002
  },
  {
    "y": "726",
    "x": "840",
    "value": 0.011
  },
  {
    "y": "726",
    "x": "843",
    "value": 0.022
  },
  {
    "y": "726",
    "x": "846",
    "value": 0.029
  },
  {
    "y": "726",
    "x": "848",
    "value": 0.036
  },
  {
    "y": "726",
    "x": "851",
    "value": 0.039
  },
  {
    "y": "726",
    "x": "854",
    "value": 2.465
  },
  {
    "y": "726",
    "x": "856",
    "value": 5.393
  },
  {
    "y": "726",
    "x": "859",
    "value": 4.629
  },
  {
    "y": "726",
    "x": "862",
    "value": 3.503
  },
  {
    "y": "726",
    "x": "864",
    "value": 2.606
  },
  {
    "y": "726",
    "x": "867",
    "value": 0.033
  },
  {
    "y": "726",
    "x": "870",
    "value": 2.042
  },
  {
    "y": "726",
    "x": "872",
    "value": 4.785
  },
  {
    "y": "726",
    "x": "875",
    "value": 5.161
  },
  {
    "y": "726",
    "x": "878",
    "value": 5.086
  },
  {
    "y": "726",
    "x": "881",
    "value": 3.493
  },
  {
    "y": "726",
    "x": "883",
    "value": 1.565
  },
  {
    "y": "726",
    "x": "886",
    "value": 1.032
  },
  {
    "y": "726",
    "x": "889",
    "value": 1.264
  },
  {
    "y": "726",
    "x": "891",
    "value": 2.138
  },
  {
    "y": "726",
    "x": "894",
    "value": 3.226
  },
  {
    "y": "726",
    "x": "897",
    "value": 1.763
  },
  {
    "y": "726",
    "x": "899",
    "value": 0.016
  },
  {
    "y": "726",
    "x": "902",
    "value": 0.008
  },
  {
    "y": "726",
    "x": "905",
    "value": 0.196
  },
  {
    "y": "726",
    "x": "907",
    "value": 0.187
  },
  {
    "y": "726",
    "x": "910",
    "value": 0.146
  },
  {
    "y": "730",
    "x": "843",
    "value": 0.006
  },
  {
    "y": "730",
    "x": "846",
    "value": 0.013
  },
  {
    "y": "730",
    "x": "848",
    "value": 0.019
  },
  {
    "y": "730",
    "x": "851",
    "value": 0.02
  },
  {
    "y": "730",
    "x": "854",
    "value": 0.032
  },
  {
    "y": "730",
    "x": "856",
    "value": 1.411
  },
  {
    "y": "730",
    "x": "859",
    "value": 1.437
  },
  {
    "y": "730",
    "x": "862",
    "value": 2.01
  },
  {
    "y": "730",
    "x": "864",
    "value": 5.664
  },
  {
    "y": "730",
    "x": "867",
    "value": 2.623
  },
  {
    "y": "730",
    "x": "870",
    "value": 0.04
  },
  {
    "y": "730",
    "x": "872",
    "value": 4.527
  },
  {
    "y": "730",
    "x": "875",
    "value": 4.735
  },
  {
    "y": "730",
    "x": "878",
    "value": 3.697
  },
  {
    "y": "730",
    "x": "881",
    "value": 2.222
  },
  {
    "y": "730",
    "x": "883",
    "value": 1.334
  },
  {
    "y": "730",
    "x": "886",
    "value": 1.368
  },
  {
    "y": "730",
    "x": "889",
    "value": 1.708
  },
  {
    "y": "730",
    "x": "891",
    "value": 2.947
  },
  {
    "y": "730",
    "x": "894",
    "value": 4.063
  },
  {
    "y": "730",
    "x": "897",
    "value": 3.643
  },
  {
    "y": "730",
    "x": "899",
    "value": 1.668
  },
  {
    "y": "730",
    "x": "902",
    "value": 0.644
  },
  {
    "y": "730",
    "x": "905",
    "value": 0.538
  },
  {
    "y": "730",
    "x": "907",
    "value": 0.014
  },
  {
    "y": "730",
    "x": "910",
    "value": 0.23
  },
  {
    "y": "730",
    "x": "913",
    "value": 0.1
  },
  {
    "y": "735",
    "x": "843",
    "value": 0.002
  },
  {
    "y": "735",
    "x": "846",
    "value": 0.005
  },
  {
    "y": "735",
    "x": "848",
    "value": 0.012
  },
  {
    "y": "735",
    "x": "851",
    "value": 0.014
  },
  {
    "y": "735",
    "x": "854",
    "value": 0.019
  },
  {
    "y": "735",
    "x": "856",
    "value": 0.021
  },
  {
    "y": "735",
    "x": "859",
    "value": 0.029
  },
  {
    "y": "735",
    "x": "862",
    "value": 0.035
  },
  {
    "y": "735",
    "x": "864",
    "value": 2.845
  },
  {
    "y": "735",
    "x": "867",
    "value": 4.274
  },
  {
    "y": "735",
    "x": "870",
    "value": 3.015
  },
  {
    "y": "735",
    "x": "872",
    "value": 3.823
  },
  {
    "y": "735",
    "x": "875",
    "value": 2.784
  },
  {
    "y": "735",
    "x": "878",
    "value": 1.761
  },
  {
    "y": "735",
    "x": "881",
    "value": 1.585
  },
  {
    "y": "735",
    "x": "883",
    "value": 1.829
  },
  {
    "y": "735",
    "x": "886",
    "value": 2.01
  },
  {
    "y": "735",
    "x": "889",
    "value": 2.605
  },
  {
    "y": "735",
    "x": "891",
    "value": 3.947
  },
  {
    "y": "735",
    "x": "894",
    "value": 4.624
  },
  {
    "y": "735",
    "x": "897",
    "value": 4.143
  },
  {
    "y": "735",
    "x": "899",
    "value": 3.148
  },
  {
    "y": "735",
    "x": "902",
    "value": 1.896
  },
  {
    "y": "735",
    "x": "905",
    "value": 1.126
  },
  {
    "y": "735",
    "x": "907",
    "value": 1.025
  },
  {
    "y": "735",
    "x": "910",
    "value": 1.113
  },
  {
    "y": "735",
    "x": "913",
    "value": 1.335
  },
  {
    "y": "735",
    "x": "915",
    "value": 1.115
  },
  {
    "y": "735",
    "x": "918",
    "value": 0.56
  },
  {
    "y": "735",
    "x": "921",
    "value": 0.256
  },
  {
    "y": "739",
    "x": "843",
    "value": 0.001
  },
  {
    "y": "739",
    "x": "846",
    "value": 0.002
  },
  {
    "y": "739",
    "x": "848",
    "value": 0.007
  },
  {
    "y": "739",
    "x": "851",
    "value": 0.082
  },
  {
    "y": "739",
    "x": "854",
    "value": 0.019
  },
  {
    "y": "739",
    "x": "856",
    "value": 0.03
  },
  {
    "y": "739",
    "x": "859",
    "value": 0.037
  },
  {
    "y": "739",
    "x": "862",
    "value": 0.049
  },
  {
    "y": "739",
    "x": "864",
    "value": 2.291
  },
  {
    "y": "739",
    "x": "867",
    "value": 3.478
  },
  {
    "y": "739",
    "x": "870",
    "value": 2.876
  },
  {
    "y": "739",
    "x": "872",
    "value": 2.621
  },
  {
    "y": "739",
    "x": "875",
    "value": 2.429
  },
  {
    "y": "739",
    "x": "878",
    "value": 2.519
  },
  {
    "y": "739",
    "x": "881",
    "value": 2.819
  },
  {
    "y": "739",
    "x": "883",
    "value": 3.07
  },
  {
    "y": "739",
    "x": "886",
    "value": 3.488
  },
  {
    "y": "739",
    "x": "889",
    "value": 4.113
  },
  {
    "y": "739",
    "x": "891",
    "value": 4.638
  },
  {
    "y": "739",
    "x": "894",
    "value": 4.62
  },
  {
    "y": "739",
    "x": "897",
    "value": 4.248
  },
  {
    "y": "739",
    "x": "899",
    "value": 3.545
  },
  {
    "y": "739",
    "x": "902",
    "value": 2.68
  },
  {
    "y": "739",
    "x": "905",
    "value": 2.288
  },
  {
    "y": "739",
    "x": "907",
    "value": 2.446
  },
  {
    "y": "739",
    "x": "910",
    "value": 2.651
  },
  {
    "y": "739",
    "x": "913",
    "value": 2.198
  },
  {
    "y": "739",
    "x": "915",
    "value": 1.186
  },
  {
    "y": "739",
    "x": "918",
    "value": 0.492
  },
  {
    "y": "739",
    "x": "921",
    "value": 0.384
  },
  {
    "y": "739",
    "x": "923",
    "value": 0.158
  },
  {
    "y": "743",
    "x": "848",
    "value": 0.114
  },
  {
    "y": "743",
    "x": "851",
    "value": 0.165
  },
  {
    "y": "743",
    "x": "862",
    "value": 0.016
  },
  {
    "y": "743",
    "x": "864",
    "value": 1.577
  },
  {
    "y": "743",
    "x": "867",
    "value": 1.084
  },
  {
    "y": "743",
    "x": "872",
    "value": 0.55
  },
  {
    "y": "743",
    "x": "875",
    "value": 0.419
  },
  {
    "y": "743",
    "x": "878",
    "value": 1.402
  },
  {
    "y": "743",
    "x": "881",
    "value": 2.027
  },
  {
    "y": "743",
    "x": "883",
    "value": 2.866
  },
  {
    "y": "743",
    "x": "886",
    "value": 3.483
  },
  {
    "y": "743",
    "x": "889",
    "value": 3.804
  },
  {
    "y": "743",
    "x": "891",
    "value": 4.002
  },
  {
    "y": "743",
    "x": "894",
    "value": 4.008
  },
  {
    "y": "743",
    "x": "897",
    "value": 4.15
  },
  {
    "y": "743",
    "x": "899",
    "value": 4.494
  },
  {
    "y": "743",
    "x": "902",
    "value": 4.559
  },
  {
    "y": "743",
    "x": "905",
    "value": 4.318
  },
  {
    "y": "743",
    "x": "907",
    "value": 4.424
  },
  {
    "y": "743",
    "x": "910",
    "value": 4.763
  },
  {
    "y": "743",
    "x": "913",
    "value": 3.663
  },
  {
    "y": "743",
    "x": "915",
    "value": 1.878
  },
  {
    "y": "743",
    "x": "918",
    "value": 1.16
  },
  {
    "y": "743",
    "x": "921",
    "value": 0.937
  },
  {
    "y": "743",
    "x": "923",
    "value": 0.793
  },
  {
    "y": "743",
    "x": "926",
    "value": 0.648
  },
  {
    "y": "748",
    "x": "851",
    "value": 0.04
  },
  {
    "y": "748",
    "x": "872",
    "value": 0.333
  },
  {
    "y": "748",
    "x": "875",
    "value": 0.047
  },
  {
    "y": "748",
    "x": "878",
    "value": 0.38
  },
  {
    "y": "748",
    "x": "881",
    "value": 0.129
  },
  {
    "y": "748",
    "x": "883",
    "value": 2.048
  },
  {
    "y": "748",
    "x": "886",
    "value": 4.032
  },
  {
    "y": "748",
    "x": "889",
    "value": 4.323
  },
  {
    "y": "748",
    "x": "891",
    "value": 4.785
  },
  {
    "y": "748",
    "x": "894",
    "value": 5.237
  },
  {
    "y": "748",
    "x": "897",
    "value": 5.497
  },
  {
    "y": "748",
    "x": "899",
    "value": 5.744
  },
  {
    "y": "748",
    "x": "902",
    "value": 5.816
  },
  {
    "y": "748",
    "x": "905",
    "value": 5.591
  },
  {
    "y": "748",
    "x": "907",
    "value": 5.311
  },
  {
    "y": "748",
    "x": "910",
    "value": 4.462
  },
  {
    "y": "748",
    "x": "913",
    "value": 2.869
  },
  {
    "y": "748",
    "x": "915",
    "value": 1.573
  },
  {
    "y": "748",
    "x": "918",
    "value": 1.059
  },
  {
    "y": "748",
    "x": "921",
    "value": 0.995
  },
  {
    "y": "748",
    "x": "923",
    "value": 1.169
  },
  {
    "y": "748",
    "x": "926",
    "value": 1.486
  },
  {
    "y": "748",
    "x": "929",
    "value": 0.913
  },
  {
    "y": "752",
    "x": "899",
    "value": 0.216
  },
  {
    "y": "752",
    "x": "902",
    "value": 0.186
  },
  {
    "y": "752",
    "x": "905",
    "value": 0.206
  },
  {
    "y": "752",
    "x": "913",
    "value": 0.496
  },
  {
    "y": "752",
    "x": "915",
    "value": 0.738
  },
  {
    "y": "752",
    "x": "918",
    "value": 0.65
  },
  {
    "y": "752",
    "x": "921",
    "value": 0.357
  },
  {
    "y": "752",
    "x": "923",
    "value": 1.106
  },
  {
    "y": "752",
    "x": "926",
    "value": 1.972
  },
  {
    "y": "752",
    "x": "929",
    "value": 2.904
  },
  {
    "y": "752",
    "x": "932",
    "value": 3.282
  },
  {
    "y": "752",
    "x": "934",
    "value": 3.104
  },
  {
    "y": "752",
    "x": "937",
    "value": 2.848
  },
  {
    "y": "752",
    "x": "940",
    "value": 2.014
  },
  {
    "y": "757",
    "x": "926",
    "value": 1.245
  },
  {
    "y": "757",
    "x": "929",
    "value": 2.926
  },
  {
    "y": "757",
    "x": "932",
    "value": 3.44
  },
  {
    "y": "757",
    "x": "934",
    "value": 3.51
  },
  {
    "y": "757",
    "x": "937",
    "value": 4.045
  },
  {
    "y": "757",
    "x": "940",
    "value": 4.6
  },
  {
    "y": "757",
    "x": "942",
    "value": 2.957
  },
  {
    "y": "757",
    "x": "945",
    "value": 1.294
  },
  {
    "y": "757",
    "x": "964",
    "value": 0.067
  },
  {
    "y": "761",
    "x": "937",
    "value": 1.472
  },
  {
    "y": "761",
    "x": "940",
    "value": 2.539
  },
  {
    "y": "761",
    "x": "942",
    "value": 1.51
  },
  {
    "y": "761",
    "x": "945",
    "value": 1.645
  },
  {
    "y": "761",
    "x": "953",
    "value": 0.817
  },
  {
    "y": "761",
    "x": "956",
    "value": 1.554
  },
  {
    "y": "761",
    "x": "958",
    "value": 2.351
  },
  {
    "y": "761",
    "x": "961",
    "value": 2.392
  },
  {
    "y": "761",
    "x": "964",
    "value": 0.989
  },
  {
    "y": "765",
    "x": "940",
    "value": 0.526
  },
  {
    "y": "765",
    "x": "942",
    "value": 0.98
  },
  {
    "y": "765",
    "x": "945",
    "value": 1.638
  },
  {
    "y": "765",
    "x": "948",
    "value": 1.418
  },
  {
    "y": "765",
    "x": "950",
    "value": 2.126
  },
  {
    "y": "765",
    "x": "953",
    "value": 3.022
  },
  {
    "y": "765",
    "x": "956",
    "value": 3.371
  },
  {
    "y": "765",
    "x": "958",
    "value": 3.33
  },
  {
    "y": "765",
    "x": "961",
    "value": 1.865
  },
  {
    "y": "770",
    "x": "942",
    "value": 0.282
  },
  {
    "y": "770",
    "x": "945",
    "value": 1.026
  },
  {
    "y": "770",
    "x": "948",
    "value": 1.822
  },
  {
    "y": "770",
    "x": "950",
    "value": 2.313
  },
  {
    "y": "770",
    "x": "953",
    "value": 2.86
  },
  {
    "y": "770",
    "x": "956",
    "value": 3.254
  },
  {
    "y": "770",
    "x": "958",
    "value": 3.12
  },
  {
    "y": "770",
    "x": "961",
    "value": 1.619
  }
]