[
  {
    "y": "465",
    "x": "499",
    "value": 0.021
  },
  {
    "y": "465",
    "x": "583",
    "value": 0.001
  },
  {
    "y": "465",
    "x": "585",
    "value": 0.006
  },
  {
    "y": "465",
    "x": "588",
    "value": 0.021
  },
  {
    "y": "465",
    "x": "591",
    "value": 0.013
  },
  {
    "y": "469",
    "x": "494",
    "value": 0.029
  },
  {
    "y": "469",
    "x": "497",
    "value": 0.001
  },
  {
    "y": "469",
    "x": "499",
    "value": 0.027
  },
  {
    "y": "469",
    "x": "502",
    "value": 0.006
  },
  {
    "y": "469",
    "x": "583",
    "value": 0.003
  },
  {
    "y": "469",
    "x": "585",
    "value": 0.021
  },
  {
    "y": "469",
    "x": "588",
    "value": 0.056
  },
  {
    "y": "469",
    "x": "591",
    "value": 0.068
  },
  {
    "y": "469",
    "x": "593",
    "value": 0.045
  },
  {
    "y": "469",
    "x": "596",
    "value": 0.015
  },
  {
    "y": "469",
    "x": "599",
    "value": 0.012
  },
  {
    "y": "473",
    "x": "491",
    "value": 0.048
  },
  {
    "y": "473",
    "x": "494",
    "value": 0.05
  },
  {
    "y": "473",
    "x": "497",
    "value": 0.007
  },
  {
    "y": "473",
    "x": "583",
    "value": 0.002
  },
  {
    "y": "473",
    "x": "585",
    "value": 0.021
  },
  {
    "y": "473",
    "x": "588",
    "value": 0.067
  },
  {
    "y": "473",
    "x": "591",
    "value": 0.092
  },
  {
    "y": "473",
    "x": "593",
    "value": 0.114
  },
  {
    "y": "473",
    "x": "596",
    "value": 0.123
  },
  {
    "y": "473",
    "x": "599",
    "value": 0.142
  },
  {
    "y": "473",
    "x": "601",
    "value": 0.1
  },
  {
    "y": "478",
    "x": "583",
    "value": 0.003
  },
  {
    "y": "478",
    "x": "585",
    "value": 0.02
  },
  {
    "y": "478",
    "x": "588",
    "value": 0.063
  },
  {
    "y": "478",
    "x": "591",
    "value": 0.115
  },
  {
    "y": "478",
    "x": "593",
    "value": 0.103
  },
  {
    "y": "478",
    "x": "596",
    "value": 0.134
  },
  {
    "y": "478",
    "x": "599",
    "value": 0.176
  },
  {
    "y": "478",
    "x": "601",
    "value": 0.176
  },
  {
    "y": "482",
    "x": "577",
    "value": 0.056
  },
  {
    "y": "482",
    "x": "580",
    "value": 0.05
  },
  {
    "y": "482",
    "x": "583",
    "value": 0.037
  },
  {
    "y": "482",
    "x": "585",
    "value": 0.012
  },
  {
    "y": "482",
    "x": "588",
    "value": 0.081
  },
  {
    "y": "482",
    "x": "591",
    "value": 0.116
  },
  {
    "y": "482",
    "x": "593",
    "value": 0.16
  },
  {
    "y": "482",
    "x": "596",
    "value": 0.159
  },
  {
    "y": "482",
    "x": "599",
    "value": 0.202
  },
  {
    "y": "482",
    "x": "601",
    "value": 0.211
  },
  {
    "y": "487",
    "x": "481",
    "value": 0.043
  },
  {
    "y": "487",
    "x": "569",
    "value": 0.192
  },
  {
    "y": "487",
    "x": "572",
    "value": 0.163
  },
  {
    "y": "487",
    "x": "574",
    "value": 0.131
  },
  {
    "y": "487",
    "x": "577",
    "value": 0.099
  },
  {
    "y": "487",
    "x": "580",
    "value": 0.078
  },
  {
    "y": "487",
    "x": "583",
    "value": 0.059
  },
  {
    "y": "487",
    "x": "585",
    "value": 0.043
  },
  {
    "y": "487",
    "x": "588",
    "value": 0.018
  },
  {
    "y": "487",
    "x": "591",
    "value": 0.01
  },
  {
    "y": "487",
    "x": "593",
    "value": 0.161
  },
  {
    "y": "487",
    "x": "596",
    "value": 0.237
  },
  {
    "y": "487",
    "x": "599",
    "value": 0.186
  },
  {
    "y": "491",
    "x": "566",
    "value": 0.344
  },
  {
    "y": "491",
    "x": "569",
    "value": 0.286
  },
  {
    "y": "491",
    "x": "572",
    "value": 0.232
  },
  {
    "y": "491",
    "x": "574",
    "value": 0.181
  },
  {
    "y": "491",
    "x": "577",
    "value": 0.135
  },
  {
    "y": "491",
    "x": "580",
    "value": 0.102
  },
  {
    "y": "491",
    "x": "583",
    "value": 0.076
  },
  {
    "y": "491",
    "x": "585",
    "value": 0.054
  },
  {
    "y": "491",
    "x": "588",
    "value": 0.033
  },
  {
    "y": "491",
    "x": "591",
    "value": 0.008
  },
  {
    "y": "491",
    "x": "593",
    "value": 0.211
  },
  {
    "y": "491",
    "x": "596",
    "value": 0.266
  },
  {
    "y": "496",
    "x": "478",
    "value": 0.013
  },
  {
    "y": "496",
    "x": "561",
    "value": 0.801
  },
  {
    "y": "496",
    "x": "564",
    "value": 0.69
  },
  {
    "y": "496",
    "x": "566",
    "value": 0.535
  },
  {
    "y": "496",
    "x": "569",
    "value": 0.402
  },
  {
    "y": "496",
    "x": "572",
    "value": 0.304
  },
  {
    "y": "496",
    "x": "574",
    "value": 0.23
  },
  {
    "y": "496",
    "x": "577",
    "value": 0.17
  },
  {
    "y": "496",
    "x": "580",
    "value": 0.124
  },
  {
    "y": "496",
    "x": "583",
    "value": 0.091
  },
  {
    "y": "496",
    "x": "585",
    "value": 0.066
  },
  {
    "y": "496",
    "x": "588",
    "value": 0.045
  },
  {
    "y": "496",
    "x": "591",
    "value": 0.031
  },
  {
    "y": "496",
    "x": "593",
    "value": 0.004
  },
  {
    "y": "500",
    "x": "548",
    "value": 0.005
  },
  {
    "y": "500",
    "x": "556",
    "value": 2.399
  },
  {
    "y": "500",
    "x": "558",
    "value": 2.262
  },
  {
    "y": "500",
    "x": "561",
    "value": 2.265
  },
  {
    "y": "500",
    "x": "564",
    "value": 2.116
  },
  {
    "y": "500",
    "x": "566",
    "value": 1.06
  },
  {
    "y": "500",
    "x": "569",
    "value": 0.609
  },
  {
    "y": "500",
    "x": "572",
    "value": 0.402
  },
  {
    "y": "500",
    "x": "574",
    "value": 0.286
  },
  {
    "y": "500",
    "x": "577",
    "value": 0.205
  },
  {
    "y": "500",
    "x": "580",
    "value": 0.146
  },
  {
    "y": "500",
    "x": "583",
    "value": 0.105
  },
  {
    "y": "500",
    "x": "585",
    "value": 0.075
  },
  {
    "y": "500",
    "x": "588",
    "value": 0.052
  },
  {
    "y": "500",
    "x": "591",
    "value": 0.033
  },
  {
    "y": "500",
    "x": "593",
    "value": 0.016
  },
  {
    "y": "500",
    "x": "596",
    "value": 0.012
  },
  {
    "y": "500",
    "x": "599",
    "value": 0.017
  },
  {
    "y": "504",
    "x": "556",
    "value": 3.646
  },
  {
    "y": "504",
    "x": "558",
    "value": 2.463
  },
  {
    "y": "504",
    "x": "561",
    "value": 2.09
  },
  {
    "y": "504",
    "x": "564",
    "value": 1.777
  },
  {
    "y": "504",
    "x": "566",
    "value": 3.402
  },
  {
    "y": "504",
    "x": "569",
    "value": 1.165
  },
  {
    "y": "504",
    "x": "572",
    "value": 0.574
  },
  {
    "y": "504",
    "x": "574",
    "value": 0.364
  },
  {
    "y": "504",
    "x": "577",
    "value": 0.251
  },
  {
    "y": "504",
    "x": "580",
    "value": 0.174
  },
  {
    "y": "504",
    "x": "583",
    "value": 0.121
  },
  {
    "y": "504",
    "x": "585",
    "value": 0.086
  },
  {
    "y": "504",
    "x": "588",
    "value": 0.058
  },
  {
    "y": "504",
    "x": "591",
    "value": 0.037
  },
  {
    "y": "504",
    "x": "593",
    "value": 0.01
  },
  {
    "y": "504",
    "x": "596",
    "value": 0.017
  },
  {
    "y": "504",
    "x": "599",
    "value": 0.015
  },
  {
    "y": "504",
    "x": "601",
    "value": 0.006
  },
  {
    "y": "504",
    "x": "604",
    "value": 0.001
  },
  {
    "y": "504",
    "x": "607",
    "value": 0.001
  },
  {
    "y": "509",
    "x": "550",
    "value": 2.821
  },
  {
    "y": "509",
    "x": "553",
    "value": 3.153
  },
  {
    "y": "509",
    "x": "556",
    "value": 2.606
  },
  {
    "y": "509",
    "x": "558",
    "value": 2.198
  },
  {
    "y": "509",
    "x": "561",
    "value": 1.928
  },
  {
    "y": "509",
    "x": "564",
    "value": 1.887
  },
  {
    "y": "509",
    "x": "566",
    "value": 1.54
  },
  {
    "y": "509",
    "x": "569",
    "value": 3.057
  },
  {
    "y": "509",
    "x": "572",
    "value": 1.083
  },
  {
    "y": "509",
    "x": "574",
    "value": 0.497
  },
  {
    "y": "509",
    "x": "577",
    "value": 0.314
  },
  {
    "y": "509",
    "x": "580",
    "value": 0.209
  },
  {
    "y": "509",
    "x": "583",
    "value": 0.14
  },
  {
    "y": "509",
    "x": "585",
    "value": 0.096
  },
  {
    "y": "509",
    "x": "588",
    "value": 0.064
  },
  {
    "y": "509",
    "x": "591",
    "value": 0.036
  },
  {
    "y": "509",
    "x": "593",
    "value": 0.011
  },
  {
    "y": "509",
    "x": "596",
    "value": 0.019
  },
  {
    "y": "509",
    "x": "599",
    "value": 0.01
  },
  {
    "y": "509",
    "x": "601",
    "value": 0.009
  },
  {
    "y": "509",
    "x": "604",
    "value": 0.005
  },
  {
    "y": "513",
    "x": "548",
    "value": 12.618
  },
  {
    "y": "513",
    "x": "550",
    "value": 7.345
  },
  {
    "y": "513",
    "x": "553",
    "value": 4.975
  },
  {
    "y": "513",
    "x": "556",
    "value": 3.723
  },
  {
    "y": "513",
    "x": "558",
    "value": 2.876
  },
  {
    "y": "513",
    "x": "561",
    "value": 2.309
  },
  {
    "y": "513",
    "x": "564",
    "value": 1.93
  },
  {
    "y": "513",
    "x": "566",
    "value": 1.779
  },
  {
    "y": "513",
    "x": "569",
    "value": 1.421
  },
  {
    "y": "513",
    "x": "572",
    "value": 2.337
  },
  {
    "y": "513",
    "x": "574",
    "value": 0.843
  },
  {
    "y": "513",
    "x": "577",
    "value": 0.397
  },
  {
    "y": "513",
    "x": "580",
    "value": 0.246
  },
  {
    "y": "513",
    "x": "583",
    "value": 0.159
  },
  {
    "y": "513",
    "x": "585",
    "value": 0.106
  },
  {
    "y": "513",
    "x": "588",
    "value": 0.065
  },
  {
    "y": "513",
    "x": "591",
    "value": 0.029
  },
  {
    "y": "513",
    "x": "593",
    "value": 0.02
  },
  {
    "y": "513",
    "x": "596",
    "value": 0.019
  },
  {
    "y": "513",
    "x": "599",
    "value": 0.013
  },
  {
    "y": "513",
    "x": "601",
    "value": 0.013
  },
  {
    "y": "513",
    "x": "604",
    "value": 0.002
  },
  {
    "y": "513",
    "x": "607",
    "value": 0.009
  },
  {
    "y": "513",
    "x": "609",
    "value": 0.004
  },
  {
    "y": "518",
    "x": "545",
    "value": 50.001
  },
  {
    "y": "518",
    "x": "548",
    "value": 50.022
  },
  {
    "y": "518",
    "x": "550",
    "value": 21.296
  },
  {
    "y": "518",
    "x": "553",
    "value": 10.223
  },
  {
    "y": "518",
    "x": "556",
    "value": 5.949
  },
  {
    "y": "518",
    "x": "558",
    "value": 3.953
  },
  {
    "y": "518",
    "x": "561",
    "value": 2.849
  },
  {
    "y": "518",
    "x": "564",
    "value": 2.232
  },
  {
    "y": "518",
    "x": "566",
    "value": 2.073
  },
  {
    "y": "518",
    "x": "569",
    "value": 1.593
  },
  {
    "y": "518",
    "x": "572",
    "value": 1.661
  },
  {
    "y": "518",
    "x": "574",
    "value": 1.487
  },
  {
    "y": "518",
    "x": "577",
    "value": 0.558
  },
  {
    "y": "518",
    "x": "580",
    "value": 0.296
  },
  {
    "y": "518",
    "x": "583",
    "value": 0.182
  },
  {
    "y": "518",
    "x": "585",
    "value": 0.118
  },
  {
    "y": "518",
    "x": "588",
    "value": 0.055
  },
  {
    "y": "518",
    "x": "591",
    "value": 0.036
  },
  {
    "y": "518",
    "x": "593",
    "value": 0.037
  },
  {
    "y": "518",
    "x": "596",
    "value": 0.039
  },
  {
    "y": "518",
    "x": "599",
    "value": 0.037
  },
  {
    "y": "518",
    "x": "601",
    "value": 0.034
  },
  {
    "y": "518",
    "x": "604",
    "value": 0.019
  },
  {
    "y": "518",
    "x": "607",
    "value": 0.011
  },
  {
    "y": "518",
    "x": "609",
    "value": 0.006
  },
  {
    "y": "518",
    "x": "612",
    "value": 0.003
  },
  {
    "y": "518",
    "x": "615",
    "value": 0.001
  },
  {
    "y": "518",
    "x": "620",
    "value": 0.001
  },
  {
    "y": "518",
    "x": "628",
    "value": 0.005
  },
  {
    "y": "522",
    "x": "542",
    "value": 20.501
  },
  {
    "y": "522",
    "x": "599",
    "value": 0.004
  },
  {
    "y": "522",
    "x": "601",
    "value": 0.015
  },
  {
    "y": "522",
    "x": "604",
    "value": 0.015
  },
  {
    "y": "522",
    "x": "607",
    "value": 0.012
  },
  {
    "y": "522",
    "x": "609",
    "value": 0.008
  },
  {
    "y": "522",
    "x": "612",
    "value": 0.005
  },
  {
    "y": "522",
    "x": "615",
    "value": 0.003
  },
  {
    "y": "522",
    "x": "617",
    "value": 0.002
  },
  {
    "y": "522",
    "x": "620",
    "value": 0.001
  },
  {
    "y": "522",
    "x": "623",
    "value": 0.001
  },
  {
    "y": "522",
    "x": "626",
    "value": 0.001
  },
  {
    "y": "522",
    "x": "636",
    "value": 0.007
  },
  {
    "y": "527",
    "x": "540",
    "value": 45.751
  },
  {
    "y": "527",
    "x": "542",
    "value": 5.187
  },
  {
    "y": "527",
    "x": "601",
    "value": 0.009
  },
  {
    "y": "527",
    "x": "604",
    "value": 0.009
  },
  {
    "y": "527",
    "x": "607",
    "value": 0.009
  },
  {
    "y": "527",
    "x": "609",
    "value": 0.007
  },
  {
    "y": "527",
    "x": "612",
    "value": 0.004
  },
  {
    "y": "527",
    "x": "615",
    "value": 0.002
  },
  {
    "y": "527",
    "x": "617",
    "value": 0.001
  },
  {
    "y": "527",
    "x": "626",
    "value": 0.005
  },
  {
    "y": "527",
    "x": "631",
    "value": 0.001
  },
  {
    "y": "527",
    "x": "644",
    "value": 0.001
  },
  {
    "y": "531",
    "x": "537",
    "value": 1.11
  },
  {
    "y": "531",
    "x": "540",
    "value": 0.721
  },
  {
    "y": "531",
    "x": "542",
    "value": 0.285
  },
  {
    "y": "531",
    "x": "601",
    "value": 0.008
  },
  {
    "y": "531",
    "x": "604",
    "value": 0.004
  },
  {
    "y": "531",
    "x": "607",
    "value": 0.006
  },
  {
    "y": "531",
    "x": "609",
    "value": 0.006
  },
  {
    "y": "531",
    "x": "612",
    "value": 0.004
  },
  {
    "y": "531",
    "x": "615",
    "value": 0.002
  },
  {
    "y": "531",
    "x": "617",
    "value": 0.002
  },
  {
    "y": "531",
    "x": "626",
    "value": 0.003
  },
  {
    "y": "531",
    "x": "628",
    "value": 0.004
  },
  {
    "y": "531",
    "x": "636",
    "value": 0.001
  },
  {
    "y": "535",
    "x": "537",
    "value": 0.645
  },
  {
    "y": "535",
    "x": "604",
    "value": 0.001
  },
  {
    "y": "535",
    "x": "607",
    "value": 0.003
  },
  {
    "y": "535",
    "x": "609",
    "value": 0.004
  },
  {
    "y": "535",
    "x": "612",
    "value": 0.003
  },
  {
    "y": "535",
    "x": "615",
    "value": 0.002
  },
  {
    "y": "535",
    "x": "617",
    "value": 0.002
  },
  {
    "y": "535",
    "x": "620",
    "value": 0.001
  },
  {
    "y": "535",
    "x": "628",
    "value": 0.003
  },
  {
    "y": "535",
    "x": "636",
    "value": 0.002
  },
  {
    "y": "535",
    "x": "639",
    "value": 0.004
  },
  {
    "y": "535",
    "x": "663",
    "value": 0.003
  },
  {
    "y": "540",
    "x": "467",
    "value": 1.48
  },
  {
    "y": "540",
    "x": "537",
    "value": 0.223
  },
  {
    "y": "540",
    "x": "542",
    "value": 0.348
  },
  {
    "y": "540",
    "x": "604",
    "value": 0.001
  },
  {
    "y": "540",
    "x": "607",
    "value": 0.001
  },
  {
    "y": "540",
    "x": "609",
    "value": 0.002
  },
  {
    "y": "540",
    "x": "612",
    "value": 0.002
  },
  {
    "y": "540",
    "x": "615",
    "value": 0.002
  },
  {
    "y": "540",
    "x": "617",
    "value": 0.003
  },
  {
    "y": "540",
    "x": "620",
    "value": 0.001
  },
  {
    "y": "540",
    "x": "623",
    "value": 0.001
  },
  {
    "y": "540",
    "x": "626",
    "value": 0.001
  },
  {
    "y": "540",
    "x": "628",
    "value": 0.001
  },
  {
    "y": "540",
    "x": "631",
    "value": 0.001
  },
  {
    "y": "540",
    "x": "644",
    "value": 0.001
  },
  {
    "y": "540",
    "x": "647",
    "value": 0.001
  },
  {
    "y": "540",
    "x": "652",
    "value": 0.001
  },
  {
    "y": "540",
    "x": "655",
    "value": 0.002
  },
  {
    "y": "540",
    "x": "658",
    "value": 0.002
  },
  {
    "y": "540",
    "x": "660",
    "value": 0.001
  },
  {
    "y": "540",
    "x": "663",
    "value": 0.001
  },
  {
    "y": "540",
    "x": "666",
    "value": 0.002
  },
  {
    "y": "540",
    "x": "668",
    "value": 0.002
  },
  {
    "y": "540",
    "x": "679",
    "value": 0.001
  },
  {
    "y": "544",
    "x": "534",
    "value": 1.09
  },
  {
    "y": "544",
    "x": "540",
    "value": 0.001
  },
  {
    "y": "544",
    "x": "609",
    "value": 0.001
  },
  {
    "y": "544",
    "x": "612",
    "value": 0.001
  },
  {
    "y": "544",
    "x": "617",
    "value": 0.001
  },
  {
    "y": "544",
    "x": "623",
    "value": 0.001
  },
  {
    "y": "544",
    "x": "626",
    "value": 0.001
  },
  {
    "y": "544",
    "x": "628",
    "value": 0.001
  },
  {
    "y": "544",
    "x": "631",
    "value": 0.001
  },
  {
    "y": "544",
    "x": "634",
    "value": 0.001
  },
  {
    "y": "544",
    "x": "636",
    "value": 0.001
  },
  {
    "y": "544",
    "x": "639",
    "value": 0.004
  },
  {
    "y": "544",
    "x": "642",
    "value": 0.002
  },
  {
    "y": "544",
    "x": "644",
    "value": 0.005
  },
  {
    "y": "544",
    "x": "650",
    "value": 0.004
  },
  {
    "y": "544",
    "x": "671",
    "value": 0.001
  },
  {
    "y": "544",
    "x": "685",
    "value": 0.002
  },
  {
    "y": "549",
    "x": "534",
    "value": 0.364
  },
  {
    "y": "549",
    "x": "540",
    "value": 0.11
  },
  {
    "y": "549",
    "x": "612",
    "value": 0.002
  },
  {
    "y": "549",
    "x": "615",
    "value": 0.002
  },
  {
    "y": "549",
    "x": "617",
    "value": 0.004
  },
  {
    "y": "549",
    "x": "620",
    "value": 0.004
  },
  {
    "y": "549",
    "x": "623",
    "value": 0.004
  },
  {
    "y": "549",
    "x": "626",
    "value": 0.005
  },
  {
    "y": "549",
    "x": "628",
    "value": 0.006
  },
  {
    "y": "549",
    "x": "631",
    "value": 0.006
  },
  {
    "y": "549",
    "x": "634",
    "value": 0.006
  },
  {
    "y": "549",
    "x": "636",
    "value": 0.006
  },
  {
    "y": "549",
    "x": "639",
    "value": 0.006
  },
  {
    "y": "549",
    "x": "642",
    "value": 0.006
  },
  {
    "y": "549",
    "x": "644",
    "value": 0.006
  },
  {
    "y": "549",
    "x": "647",
    "value": 0.006
  },
  {
    "y": "549",
    "x": "650",
    "value": 0.006
  },
  {
    "y": "549",
    "x": "652",
    "value": 0.006
  },
  {
    "y": "549",
    "x": "655",
    "value": 0.006
  },
  {
    "y": "549",
    "x": "658",
    "value": 0.006
  },
  {
    "y": "549",
    "x": "660",
    "value": 0.007
  },
  {
    "y": "549",
    "x": "663",
    "value": 0.009
  },
  {
    "y": "549",
    "x": "666",
    "value": 0.008
  },
  {
    "y": "549",
    "x": "668",
    "value": 0.007
  },
  {
    "y": "549",
    "x": "671",
    "value": 0.005
  },
  {
    "y": "549",
    "x": "674",
    "value": 0.005
  },
  {
    "y": "549",
    "x": "677",
    "value": 0.004
  },
  {
    "y": "549",
    "x": "679",
    "value": 0.005
  },
  {
    "y": "549",
    "x": "682",
    "value": 0.004
  },
  {
    "y": "549",
    "x": "685",
    "value": 0.006
  },
  {
    "y": "549",
    "x": "687",
    "value": 0.003
  },
  {
    "y": "549",
    "x": "690",
    "value": 0.003
  },
  {
    "y": "549",
    "x": "693",
    "value": 0.002
  },
  {
    "y": "549",
    "x": "695",
    "value": 0.001
  },
  {
    "y": "549",
    "x": "698",
    "value": 0.001
  },
  {
    "y": "549",
    "x": "701",
    "value": 0.001
  },
  {
    "y": "549",
    "x": "703",
    "value": 0.012
  },
  {
    "y": "553",
    "x": "459",
    "value": 0.979
  },
  {
    "y": "553",
    "x": "532",
    "value": 1.074
  },
  {
    "y": "553",
    "x": "537",
    "value": 0.707
  },
  {
    "y": "553",
    "x": "636",
    "value": 0.001
  },
  {
    "y": "553",
    "x": "639",
    "value": 0.002
  },
  {
    "y": "553",
    "x": "642",
    "value": 0.002
  },
  {
    "y": "553",
    "x": "644",
    "value": 0.002
  },
  {
    "y": "553",
    "x": "647",
    "value": 0.003
  },
  {
    "y": "553",
    "x": "650",
    "value": 0.003
  },
  {
    "y": "553",
    "x": "652",
    "value": 0.003
  },
  {
    "y": "553",
    "x": "655",
    "value": 0.002
  },
  {
    "y": "553",
    "x": "658",
    "value": 0.002
  },
  {
    "y": "553",
    "x": "660",
    "value": 0.002
  },
  {
    "y": "553",
    "x": "663",
    "value": 0.002
  },
  {
    "y": "553",
    "x": "666",
    "value": 0.001
  },
  {
    "y": "553",
    "x": "668",
    "value": 0.001
  },
  {
    "y": "553",
    "x": "671",
    "value": 0.001
  },
  {
    "y": "553",
    "x": "674",
    "value": 0.002
  },
  {
    "y": "553",
    "x": "677",
    "value": 0.002
  },
  {
    "y": "553",
    "x": "679",
    "value": 0.003
  },
  {
    "y": "553",
    "x": "682",
    "value": 0.004
  },
  {
    "y": "553",
    "x": "685",
    "value": 0.005
  },
  {
    "y": "553",
    "x": "687",
    "value": 0.003
  },
  {
    "y": "553",
    "x": "690",
    "value": 0.003
  },
  {
    "y": "553",
    "x": "693",
    "value": 0.004
  },
  {
    "y": "553",
    "x": "695",
    "value": 0.004
  },
  {
    "y": "553",
    "x": "698",
    "value": 0.003
  },
  {
    "y": "553",
    "x": "701",
    "value": 0.001
  },
  {
    "y": "553",
    "x": "703",
    "value": 0.003
  },
  {
    "y": "558",
    "x": "459",
    "value": 0.566
  },
  {
    "y": "558",
    "x": "529",
    "value": 1.086
  },
  {
    "y": "558",
    "x": "666",
    "value": 0.001
  },
  {
    "y": "558",
    "x": "679",
    "value": 0.002
  },
  {
    "y": "558",
    "x": "682",
    "value": 0.001
  },
  {
    "y": "558",
    "x": "703",
    "value": 0.001
  },
  {
    "y": "562",
    "x": "456",
    "value": 0.899
  },
  {
    "y": "562",
    "x": "526",
    "value": 1.093
  },
  {
    "y": "562",
    "x": "532",
    "value": 2.063
  },
  {
    "y": "562",
    "x": "687",
    "value": 0.005
  },
  {
    "y": "562",
    "x": "701",
    "value": 0.001
  },
  {
    "y": "562",
    "x": "703",
    "value": 0.001
  },
  {
    "y": "562",
    "x": "706",
    "value": 0.002
  },
  {
    "y": "562",
    "x": "709",
    "value": 0.002
  },
  {
    "y": "562",
    "x": "711",
    "value": 0.002
  },
  {
    "y": "562",
    "x": "714",
    "value": 0.002
  },
  {
    "y": "566",
    "x": "523",
    "value": 1.106
  },
  {
    "y": "566",
    "x": "529",
    "value": 0.315
  },
  {
    "y": "566",
    "x": "711",
    "value": 0.002
  },
  {
    "y": "566",
    "x": "714",
    "value": 0.003
  },
  {
    "y": "566",
    "x": "717",
    "value": 0.003
  },
  {
    "y": "566",
    "x": "719",
    "value": 0.003
  },
  {
    "y": "571",
    "x": "454",
    "value": 0.328
  },
  {
    "y": "571",
    "x": "521",
    "value": 0.356
  },
  {
    "y": "571",
    "x": "526",
    "value": 0.008
  },
  {
    "y": "571",
    "x": "703",
    "value": 0.003
  },
  {
    "y": "571",
    "x": "711",
    "value": 0.002
  },
  {
    "y": "571",
    "x": "714",
    "value": 0.003
  },
  {
    "y": "571",
    "x": "717",
    "value": 0.004
  },
  {
    "y": "571",
    "x": "719",
    "value": 0.003
  },
  {
    "y": "575",
    "x": "451",
    "value": 1.474
  },
  {
    "y": "575",
    "x": "521",
    "value": 0.331
  },
  {
    "y": "575",
    "x": "523",
    "value": 0.001
  },
  {
    "y": "575",
    "x": "711",
    "value": 0.001
  },
  {
    "y": "575",
    "x": "714",
    "value": 0.004
  },
  {
    "y": "575",
    "x": "717",
    "value": 0.006
  },
  {
    "y": "575",
    "x": "719",
    "value": 0.005
  },
  {
    "y": "575",
    "x": "722",
    "value": 0.002
  },
  {
    "y": "575",
    "x": "725",
    "value": 0.001
  },
  {
    "y": "575",
    "x": "738",
    "value": 0.002
  },
  {
    "y": "580",
    "x": "451",
    "value": 0.451
  },
  {
    "y": "580",
    "x": "518",
    "value": 0.252
  },
  {
    "y": "580",
    "x": "714",
    "value": 0.003
  },
  {
    "y": "580",
    "x": "717",
    "value": 0.003
  },
  {
    "y": "580",
    "x": "719",
    "value": 0.004
  },
  {
    "y": "580",
    "x": "722",
    "value": 0.003
  },
  {
    "y": "580",
    "x": "725",
    "value": 0.001
  },
  {
    "y": "580",
    "x": "728",
    "value": 0.001
  },
  {
    "y": "580",
    "x": "730",
    "value": 0.001
  },
  {
    "y": "580",
    "x": "733",
    "value": 0.002
  },
  {
    "y": "580",
    "x": "736",
    "value": 0.001
  },
  {
    "y": "584",
    "x": "515",
    "value": 0.35
  },
  {
    "y": "584",
    "x": "717",
    "value": 0.001
  },
  {
    "y": "584",
    "x": "746",
    "value": 0.001
  },
  {
    "y": "584",
    "x": "749",
    "value": 0.001
  },
  {
    "y": "588",
    "x": "448",
    "value": 0.608
  },
  {
    "y": "588",
    "x": "513",
    "value": 0.627
  },
  {
    "y": "588",
    "x": "515",
    "value": 1.222
  },
  {
    "y": "588",
    "x": "738",
    "value": 0.001
  },
  {
    "y": "588",
    "x": "741",
    "value": 0.001
  },
  {
    "y": "593",
    "x": "448",
    "value": 0.356
  },
  {
    "y": "593",
    "x": "510",
    "value": 1.201
  },
  {
    "y": "593",
    "x": "741",
    "value": 0.001
  },
  {
    "y": "597",
    "x": "446",
    "value": 0.555
  },
  {
    "y": "597",
    "x": "448",
    "value": 0.345
  },
  {
    "y": "597",
    "x": "505",
    "value": 0.358
  },
  {
    "y": "597",
    "x": "507",
    "value": 0.091
  },
  {
    "y": "597",
    "x": "738",
    "value": 0.003
  },
  {
    "y": "602",
    "x": "502",
    "value": 0.299
  },
  {
    "y": "602",
    "x": "505",
    "value": 1.2
  },
  {
    "y": "602",
    "x": "773",
    "value": 0.003
  },
  {
    "y": "606",
    "x": "499",
    "value": 0.248
  },
  {
    "y": "606",
    "x": "502",
    "value": 1.228
  },
  {
    "y": "606",
    "x": "757",
    "value": 0.001
  },
  {
    "y": "611",
    "x": "448",
    "value": 0.438
  },
  {
    "y": "611",
    "x": "494",
    "value": 0.155
  },
  {
    "y": "611",
    "x": "497",
    "value": 0.74
  },
  {
    "y": "611",
    "x": "754",
    "value": 0.001
  },
  {
    "y": "611",
    "x": "762",
    "value": 0.003
  },
  {
    "y": "611",
    "x": "765",
    "value": 0.004
  },
  {
    "y": "611",
    "x": "768",
    "value": 0.006
  },
  {
    "y": "611",
    "x": "770",
    "value": 0.007
  },
  {
    "y": "611",
    "x": "773",
    "value": 0.001
  },
  {
    "y": "611",
    "x": "781",
    "value": 0.003
  },
  {
    "y": "615",
    "x": "491",
    "value": 0.466
  },
  {
    "y": "615",
    "x": "754",
    "value": 0.001
  },
  {
    "y": "615",
    "x": "757",
    "value": 0.001
  },
  {
    "y": "615",
    "x": "776",
    "value": 0.001
  },
  {
    "y": "615",
    "x": "779",
    "value": 0.002
  },
  {
    "y": "615",
    "x": "781",
    "value": 0.002
  },
  {
    "y": "619",
    "x": "489",
    "value": 0.17
  },
  {
    "y": "619",
    "x": "760",
    "value": 0.001
  },
  {
    "y": "619",
    "x": "762",
    "value": 0.001
  },
  {
    "y": "619",
    "x": "765",
    "value": 0.001
  },
  {
    "y": "619",
    "x": "768",
    "value": 0.001
  },
  {
    "y": "619",
    "x": "770",
    "value": 0.001
  },
  {
    "y": "619",
    "x": "773",
    "value": 0.001
  },
  {
    "y": "619",
    "x": "776",
    "value": 0.002
  },
  {
    "y": "619",
    "x": "779",
    "value": 0.001
  },
  {
    "y": "619",
    "x": "781",
    "value": 0.001
  },
  {
    "y": "624",
    "x": "762",
    "value": 0.001
  },
  {
    "y": "624",
    "x": "773",
    "value": 0.001
  },
  {
    "y": "628",
    "x": "475",
    "value": 0.211
  },
  {
    "y": "628",
    "x": "776",
    "value": 0.001
  },
  {
    "y": "628",
    "x": "792",
    "value": 0.001
  },
  {
    "y": "633",
    "x": "795",
    "value": 0.001
  },
  {
    "y": "642",
    "x": "792",
    "value": 0.001
  },
  {
    "y": "646",
    "x": "792",
    "value": 0.001
  },
  {
    "y": "646",
    "x": "795",
    "value": 0.001
  },
  {
    "y": "655",
    "x": "792",
    "value": 0.002
  },
  {
    "y": "659",
    "x": "792",
    "value": 0.001
  },
  {
    "y": "664",
    "x": "795",
    "value": 0.002
  },
  {
    "y": "668",
    "x": "795",
    "value": 0.001
  },
  {
    "y": "686",
    "x": "800",
    "value": 0.001
  },
  {
    "y": "686",
    "x": "803",
    "value": 0.002
  },
  {
    "y": "686",
    "x": "805",
    "value": 0.001
  },
  {
    "y": "690",
    "x": "800",
    "value": 0.001
  },
  {
    "y": "690",
    "x": "803",
    "value": 0.002
  },
  {
    "y": "690",
    "x": "805",
    "value": 0.001
  }
]